{"d": {"0KQjgM37jyNJ8NaMz92KUlidE1t2": {"name": "32GB", "oldGP": 16680, "newGP": 17260, "gpChange": 580, "loggedIn": "Yes", "notes": "", "logoutStreak": 0}, "0SMgDRVeyyWEBnXL6BTnkMp9cqA2": {"name": "BurritoTorpido", "oldGP": 0, "newGP": 520, "gpChange": 520, "loggedIn": "Yes", "notes": "New member", "logoutStreak": 0}, "128qMIHzeRZCAl6RRnKrJxU0qRS2": {"name": "Cernil", "oldGP": 7640, "newGP": 8280, "gpChange": 640, "loggedIn": "Yes", "notes": "", "logoutStreak": 0}, "2azichISmicGZFcMQgtgfQ1blJX2": {"name": "shinynew", "oldGP": 21990, "newGP": 22390, "gpChange": 400, "loggedIn": "Yes", "notes": "", "logoutStreak": 0}, "2jqMOlAGQkV63IjyEBqcloS8Nv42": {"name": "blackshadow54", "oldGP": 2800, "newGP": 3220, "gpChange": 420, "loggedIn": "Yes", "notes": "", "logoutStreak": 0}, "2wpNSr4g3CU8vj0JVxBe3Kjb4Zn2": {"name": "The_Noobzz", "oldGP": 350, "newGP": 410, "gpChange": 60, "loggedIn": "Yes", "notes": "", "logoutStreak": 0}, "3FvV8h4FHOX61BWf4VCaOhIlXKq2": {"name": "notclassman", "oldGP": 10400, "newGP": 10720, "gpChange": 320, "loggedIn": "Yes", "notes": "", "logoutStreak": 0}, "3N18BOMaPda1iX7cMdBPyuGJnED2": {"name": "cheira_tomate", "oldGP": 26210, "newGP": 26770, "gpChange": 560, "loggedIn": "Yes", "notes": "", "logoutStreak": 0}, "3nh6tPxNsgffuEAbGitUmso9pD93": {"name": "alien1154", "oldGP": 14300, "newGP": 14610, "gpChange": 310, "loggedIn": "Yes", "notes": "", "logoutStreak": 0}, "3xFX9FgXMnd8EcCC6GpZ5TNI9Qv2": {"name": "VOLXIN", "oldGP": 20170, "newGP": 20720, "gpChange": 550, "loggedIn": "Yes", "notes": "", "logoutStreak": 0}, "4YzjpaKGQcQb5Ze3Xn848se4JMh2": {"name": "Armday247", "oldGP": 5090, "newGP": 5530, "gpChange": 440, "loggedIn": "Yes", "notes": "", "logoutStreak": 0}, "4fri7GibGCNPMdWB2U1MuJbihRR2": {"name": "NoseBleeder", "oldGP": 29690, "newGP": 30410, "gpChange": 720, "loggedIn": "Yes", "notes": "", "logoutStreak": 0}, "4mlottCPskPVEmUgQNhY7w4oHD12": {"name": "wizardyname", "oldGP": 25300, "newGP": 25880, "gpChange": 580, "loggedIn": "Yes", "notes": "", "logoutStreak": 0}, "4tgVhsAT19YixJvXeUPYV8YuH7H3": {"name": "RikarudohMiner", "oldGP": 18600, "newGP": 240, "gpChange": -18360, "loggedIn": "Yes", "notes": "Name change (Old name: RikarudohJour)", "logoutStreak": 0}, "5HcrECWSFSPSymIQG6zDD2TdCdJ3": {"name": "Xenogenics", "oldGP": 0, "newGP": 580, "gpChange": 580, "loggedIn": "Yes", "notes": "New member", "logoutStreak": 0}, "5NbiVHPoqDaIun7ZdVq8fqrSW4C2": {"name": "KarlFist", "oldGP": 15360, "newGP": 15740, "gpChange": 380, "loggedIn": "Yes", "notes": "", "logoutStreak": 0}, "6I33tURa7RX93u1XH1kXh1xZmOa2": {"name": "luckE_E", "oldGP": 1460, "newGP": 1830, "gpChange": 370, "loggedIn": "Yes", "notes": "", "logoutStreak": 0}, "6eyoLAiRknYVgFArK94whX9s1HQ2": {"name": "c9_Guac", "oldGP": 13790, "newGP": 14190, "gpChange": 400, "loggedIn": "Yes", "notes": "", "logoutStreak": 0}, "7ObTQub2TmcTSQvLLB0ICQTTYof1": {"name": "SquireTheBoB", "oldGP": 930, "newGP": 1530, "gpChange": 600, "loggedIn": "Yes", "notes": "", "logoutStreak": 0}, "7QuxPQiGi0NGzf6vfxL8py7gOp72": {"name": "Gorbers", "oldGP": 15510, "newGP": 16000, "gpChange": 490, "loggedIn": "Yes", "notes": "", "logoutStreak": 0}, "7f8uziAoeTXh3wBtaQG6Df2dJ9Q2": {"name": "veraphix", "oldGP": 31060, "newGP": 31750, "gpChange": 690, "loggedIn": "Yes", "notes": "", "logoutStreak": 0}, "8ad174NeTkaxMlEaR6osPrh6LEw1": {"name": "99Slayer", "oldGP": 18138, "newGP": 18588, "gpChange": 450, "loggedIn": "Yes", "notes": "", "logoutStreak": 0}, "97nx8dAkKSM4E4iqaTPaj0wF5DP2": {"name": "Velnya", "oldGP": 11100, "newGP": 11540, "gpChange": 440, "loggedIn": "Yes", "notes": "", "logoutStreak": 0}, "9SCiGlLW3NSDiDq0FGWNSFofD3U2": {"name": "Marcsterisboss", "oldGP": 13540, "newGP": 13760, "gpChange": 220, "loggedIn": "Yes", "notes": "", "logoutStreak": 0}, "AblMpnyvH3QigsA15gNCdFMtjeE2": {"name": "Bigskillerboi", "oldGP": 4920, "newGP": 5340, "gpChange": 420, "loggedIn": "Yes", "notes": "", "logoutStreak": 0}, "BK3TzPZeO7UB9vbKyd0h0OME1VE2": {"name": "minsoup", "oldGP": 15010, "newGP": 15450, "gpChange": 440, "loggedIn": "Yes", "notes": "", "logoutStreak": 0}, "BRiucZLshKbqxP4fzK2SmvCwYpf1": {"name": "gabotupixd4", "oldGP": 12220, "newGP": 12700, "gpChange": 480, "loggedIn": "Yes", "notes": "", "logoutStreak": 0}, "CQZvPjhCC4U17xW2tlasYjQ0aGU2": {"name": "egdsgbsbg", "oldGP": 13978, "newGP": 14388, "gpChange": 410, "loggedIn": "Yes", "notes": "", "logoutStreak": 0}, "CWauSvBg4bb1GCkXZV2AGPIU6nG3": {"name": "SiopBow", "oldGP": 1670, "newGP": 2350, "gpChange": 680, "loggedIn": "Yes", "notes": "", "logoutStreak": 0}, "DGu9z4WIC1SgxdTeptNmGX1hxkt1": {"name": "melchiorv", "oldGP": 26460, "newGP": 27140, "gpChange": 680, "loggedIn": "Yes", "notes": "", "logoutStreak": 0}, "DNrVb6n6Pububn9CdBtQFTk3ELw1": {"name": "Kidkrall_main", "oldGP": 3020, "newGP": 3350, "gpChange": 330, "loggedIn": "Yes", "notes": "", "logoutStreak": 0}, "DoxPDnhgqwcjfNmNDgiyZJkaaDO2": {"name": "mageatton", "oldGP": 8750, "newGP": 9190, "gpChange": 440, "loggedIn": "Yes", "notes": "", "logoutStreak": 0}, "E2KgM3ihlJNCjAMm5OenAyHagMt2": {"name": "yoness2005", "oldGP": 17950, "newGP": 18370, "gpChange": 420, "loggedIn": "Yes", "notes": "", "logoutStreak": 0}, "EFt5po1wAmVmJC1fae6sQfUYilD3": {"name": "circleclicker", "oldGP": 19950, "newGP": 20380, "gpChange": 430, "loggedIn": "Yes", "notes": "", "logoutStreak": 0}, "EZY8JQjfv9Pnqda9hRajEUaFCoY2": {"name": "Calamares", "oldGP": 13040, "newGP": 13370, "gpChange": 330, "loggedIn": "Yes", "notes": "", "logoutStreak": 0}, "F46J2TSjKONfZrGfMqedBfle7Y33": {"name": "scarpy03_v5", "oldGP": 3980, "newGP": 4420, "gpChange": 440, "loggedIn": "Yes", "notes": "", "logoutStreak": 0}, "FbA4oAN7QIOfurX8IxFqwk2hlgn2": {"name": "Billazedd", "oldGP": 17020, "newGP": 17880, "gpChange": 860, "loggedIn": "Yes", "notes": "", "logoutStreak": 0}, "FeehrSvzHrgpytXYDJlER99nHY83": {"name": "Jimbolim", "oldGP": 310, "newGP": 900, "gpChange": 590, "loggedIn": "Yes", "notes": "", "logoutStreak": 0}, "HSl8DidmOQXS8H0iTYTke9XW9qa2": {"name": "wiarre", "oldGP": 1370, "newGP": 1730, "gpChange": 360, "loggedIn": "Yes", "notes": "", "logoutStreak": 0}, "IqEPmfUyoBc2p2WGkonGkamUgvf1": {"name": "MattRyan", "oldGP": 17520, "newGP": 17850, "gpChange": 330, "loggedIn": "Yes", "notes": "", "logoutStreak": 0}, "IuqmA3Qw6fTcJ6MESzAUZ1imOPX2": {"name": "jacobalo", "oldGP": 28570, "newGP": 29160, "gpChange": 590, "loggedIn": "Yes", "notes": "", "logoutStreak": 0}, "KcdFe7Gp19QoxUhOytzT9e6bSVw2": {"name": "eman_reyalp123", "oldGP": 16970, "newGP": 17290, "gpChange": 320, "loggedIn": "Yes", "notes": "", "logoutStreak": 0}, "Kq1cADZKdEfsmxDW7l73Te2SKWJ3": {"name": "SparkyWar", "oldGP": 690, "newGP": 890, "gpChange": 200, "loggedIn": "Yes", "notes": "", "logoutStreak": 0}, "KraniII9A3gFNgxWfmGUm1TKe7H2": {"name": "TheGamblingKun", "oldGP": 22100, "newGP": 23340, "gpChange": 1240, "loggedIn": "Yes", "notes": "", "logoutStreak": 0}, "LUTNo2VkOKcec6NNgVFgXgGoIJX2": {"name": "genderstick", "oldGP": 17830, "newGP": 18230, "gpChange": 400, "loggedIn": "Yes", "notes": "", "logoutStreak": 0}, "LiNUcR5dI0U6mPUvenDbn0DuauI2": {"name": "Sokozero", "oldGP": 580, "newGP": 820, "gpChange": 240, "loggedIn": "Yes", "notes": "", "logoutStreak": 0}, "LiSeqqQ0DLNG1gcce4oyTrRIY6I2": {"name": "Magic_Jimmy", "oldGP": 850, "newGP": 1340, "gpChange": 490, "loggedIn": "Yes", "notes": "", "logoutStreak": 0}, "M7vtvpUi1pZ65GEjBylg2arLCUq2": {"name": "archerdoode9", "oldGP": 4880, "newGP": 5310, "gpChange": 430, "loggedIn": "Yes", "notes": "", "logoutStreak": 0}, "McN6NhfEcJdCmBIkw5F2R2NtVkF3": {"name": "qbpakman", "oldGP": 12170, "newGP": 12430, "gpChange": 260, "loggedIn": "Yes", "notes": "", "logoutStreak": 0}, "NgMQUTstogcRm9UisASwwNYpCux2": {"name": "Sinsoloo", "oldGP": 500, "newGP": 910, "gpChange": 410, "loggedIn": "Yes", "notes": "", "logoutStreak": 0}, "O3xFk8Gj84YifL2PmRuF9zEerkX2": {"name": "Dappur", "oldGP": 7580, "newGP": 7970, "gpChange": 390, "loggedIn": "Yes", "notes": "", "logoutStreak": 0}, "O4iL1tVBeLhTNJapu9sTyoxXZYq1": {"name": "PsychBuff", "oldGP": 15650, "newGP": 15990, "gpChange": 340, "loggedIn": "Yes", "notes": "", "logoutStreak": 0}, "OOFJ5ZWhJYWRwsXzHb0F8Ipjl3C2": {"name": "Littleoz", "oldGP": 1270, "newGP": 1770, "gpChange": 500, "loggedIn": "Yes", "notes": "", "logoutStreak": 0}, "OepRYfHwzNYkxwDq1jEF6YHHDhb2": {"name": "Alcariya", "oldGP": 15340, "newGP": 15810, "gpChange": 470, "loggedIn": "Yes", "notes": "", "logoutStreak": 0}, "OzGgM5oHSicZyPlwOeHohUTD3th1": {"name": "Jelly48", "oldGP": 9630, "newGP": 10060, "gpChange": 430, "loggedIn": "Yes", "notes": "", "logoutStreak": 0}, "PAkJzMrwi6Oj5kfOgAniyGdidtX2": {"name": "gloopsyman", "oldGP": 9260, "newGP": 9680, "gpChange": 420, "loggedIn": "Yes", "notes": "", "logoutStreak": 0}, "PD3oWqKcWfgP17MGNC5NdDvG0es1": {"name": "Cross_Angel9", "oldGP": 12390, "newGP": 12720, "gpChange": 330, "loggedIn": "Yes", "notes": "", "logoutStreak": 0}, "PLUNoC6XnERWQNu4FXIcyrAuQF62": {"name": "PhantomMoo", "oldGP": 25040, "newGP": 25490, "gpChange": 450, "loggedIn": "Yes", "notes": "", "logoutStreak": 0}, "PLX9tmoJIgMKlbTNg987S0K0vom1": {"name": "Z3R0ARR0WS", "oldGP": 0, "newGP": 530, "gpChange": 530, "loggedIn": "Yes", "notes": "New member", "logoutStreak": 0}, "PeDP15VokFRhmqL6oVPg5MBbPFZ2": {"name": "Nillereight", "oldGP": 3920, "newGP": 4340, "gpChange": 420, "loggedIn": "Yes", "notes": "", "logoutStreak": 0}, "Q1bhnoYzsNNogrgpLquj17APLGs2": {"name": "dyamain", "oldGP": 840, "newGP": 1270, "gpChange": 430, "loggedIn": "Yes", "notes": "", "logoutStreak": 0}, "Q8bgwHZGXzNDnL5zkAx1rwXlyFh2": {"name": "youknowself", "oldGP": 0, "newGP": 490, "gpChange": 490, "loggedIn": "Yes", "notes": "New member", "logoutStreak": 0}, "QGQ4XrkesmRJDLyX8hCeYcCkS6V2": {"name": "energz", "oldGP": 16170, "newGP": 16380, "gpChange": 210, "loggedIn": "Yes", "notes": "", "logoutStreak": 0}, "QGt00zySetNDLMrquFjwSXQPpru1": {"name": "sesd142", "oldGP": 3880, "newGP": 4310, "gpChange": 430, "loggedIn": "Yes", "notes": "", "logoutStreak": 0}, "QHAEJz2ZDjVUZeI97ZG0jzqLJky1": {"name": "agi2bnuts", "oldGP": 600, "newGP": 1130, "gpChange": 530, "loggedIn": "Yes", "notes": "", "logoutStreak": 0}, "QIaBBR8IYyVhFCbhQnjo2etNyj52": {"name": "thepunisher678", "oldGP": 6330, "newGP": 6790, "gpChange": 460, "loggedIn": "Yes", "notes": "", "logoutStreak": 0}, "RFVuOXDjNdTTaMbk87j8X5xM5kq1": {"name": "2d_ninja", "oldGP": 1280, "newGP": 1670, "gpChange": 390, "loggedIn": "Yes", "notes": "", "logoutStreak": 0}, "RS6zSGGsJzZu568SQIeq5EWpSaV2": {"name": "Glyphls", "oldGP": 830, "newGP": 1230, "gpChange": 400, "loggedIn": "Yes", "notes": "", "logoutStreak": 0}, "Ra0ctE1M4EcGlFSfjcfP4lG8ZWx2": {"name": "LiquefiedPanda", "oldGP": 5190, "newGP": 5700, "gpChange": 510, "loggedIn": "Yes", "notes": "", "logoutStreak": 0}, "RhWgtQg21KVqwzWNWX8ounDjN1a2": {"name": "XHyerX", "oldGP": 0, "newGP": 360, "gpChange": 360, "loggedIn": "Yes", "notes": "New member", "logoutStreak": 0}, "RyD0XF66dvcHg3wesql93mf0EWf2": {"name": "Chrones", "oldGP": 12930, "newGP": 13250, "gpChange": 320, "loggedIn": "Yes", "notes": "", "logoutStreak": 0}, "SJAtO2Oni8UyUMZFe0KC2SA94Rw2": {"name": "Zaphord", "oldGP": 13190, "newGP": 13530, "gpChange": 340, "loggedIn": "Yes", "notes": "", "logoutStreak": 0}, "SdcO0wOJJjQt3njaBMK80m2LbMy1": {"name": "slopyjoe1", "oldGP": 4150, "newGP": 4260, "gpChange": 110, "loggedIn": "Yes", "notes": "", "logoutStreak": 0}, "T2lYDNdFo3QN0PZ3TOIAmdM2aeo1": {"name": "Eregerhn", "oldGP": 1210, "newGP": 1940, "gpChange": 730, "loggedIn": "Yes", "notes": "", "logoutStreak": 0}, "Tk9WneepFXOSomAfMNC7K6yeHgr2": {"name": "Didlzz", "oldGP": 16880, "newGP": 17240, "gpChange": 360, "loggedIn": "Yes", "notes": "", "logoutStreak": 0}, "UMCUwZeBLMgk7AUDfFzlsNTnHZF2": {"name": "Rwolflord", "oldGP": 11020, "newGP": 11060, "gpChange": 40, "loggedIn": "Yes", "notes": "", "logoutStreak": 0}, "UPFeJRvwfeTpsuBrRzLrPFADSQ93": {"name": "Scholar_Teddo", "oldGP": 17100, "newGP": 17430, "gpChange": 330, "loggedIn": "Yes", "notes": "", "logoutStreak": 0}, "V1elYbQtrJbWPlaeQ2W9jLbqpml1": {"name": "Bridgj7", "oldGP": 13530, "newGP": 13990, "gpChange": 460, "loggedIn": "Yes", "notes": "", "logoutStreak": 0}, "V5XPJoPMqpZlTO8SyGpOrtS6Y2R2": {"name": "stinky_bootty", "oldGP": 21710, "newGP": 22280, "gpChange": 570, "loggedIn": "Yes", "notes": "", "logoutStreak": 0}, "VENMQeLApRTfUmaNVxfDoSylobq2": {"name": "StompJourney", "oldGP": 4000, "newGP": 4310, "gpChange": 310, "loggedIn": "Yes", "notes": "", "logoutStreak": 0}, "ViBjUOrBDyTwut1cqbtjKBqNGgY2": {"name": "Gamba_Mage", "oldGP": 16510, "newGP": 16960, "gpChange": 450, "loggedIn": "Yes", "notes": "", "logoutStreak": 0}, "WMtChMqUhGNp4YJYIa8N9Tc45lp2": {"name": "ACPhoenix1", "oldGP": 16710, "newGP": 17180, "gpChange": 470, "loggedIn": "Yes", "notes": "", "logoutStreak": 0}, "WQm8d7Lp7YTUrqCDLiqLLUKP8mC3": {"name": "IsekaiMage", "oldGP": 19430, "newGP": 20160, "gpChange": 730, "loggedIn": "Yes", "notes": "", "logoutStreak": 0}, "XqFf7i7Cj7d9ZgT64JPaTvSCwf73": {"name": "Sajalik2", "oldGP": 17850, "newGP": 18300, "gpChange": 450, "loggedIn": "Yes", "notes": "", "logoutStreak": 0}, "Yk4VIsftUkQ3b0eoUA3HNHymMMY2": {"name": "EmilieStr", "oldGP": 12030, "newGP": 12400, "gpChange": 370, "loggedIn": "Yes", "notes": "", "logoutStreak": 0}, "YkLPe6zHCVTTM0bXmJmkfdUR1412": {"name": "LeoooZ", "oldGP": 1920, "newGP": 2070, "gpChange": 150, "loggedIn": "Yes", "notes": "", "logoutStreak": 0}, "YpNvW7I1wAVaQN2Hrn6bj9Y175o1": {"name": "Calandros", "oldGP": 3080, "newGP": 3400, "gpChange": 320, "loggedIn": "Yes", "notes": "", "logoutStreak": 0}, "Ys7nULLLfhgo7B4lzny4R7Jbb7W2": {"name": "Mr_Geoff", "oldGP": 5770, "newGP": 6230, "gpChange": 460, "loggedIn": "Yes", "notes": "", "logoutStreak": 0}, "ZFPXoh0BlYSlm4mfgZycTH9l13f1": {"name": "Drukez", "oldGP": 7500, "newGP": 8130, "gpChange": 630, "loggedIn": "Yes", "notes": "", "logoutStreak": 0}, "ZGa7TjJrcyTqYoUyKSFaOtxioqg2": {"name": "HUNGRYJACKS", "oldGP": 25570, "newGP": 26220, "gpChange": 650, "loggedIn": "Yes", "notes": "", "logoutStreak": 0}, "ZIXqHKql66Pn9ufc4GK1oNCTqa12": {"name": "IllusionOfSkill", "oldGP": 7430, "newGP": 7820, "gpChange": 390, "loggedIn": "Yes", "notes": "", "logoutStreak": 0}, "ZlbBXzagVBbShS61JXrKkod4F103": {"name": "Goku9plooooo0", "oldGP": 9910, "newGP": 10030, "gpChange": 120, "loggedIn": "Yes", "notes": "", "logoutStreak": 0}, "ZuAkMC4beoZZbiOJDUsR4KzCw0B3": {"name": "WeShallPvP", "oldGP": 12840, "newGP": 13230, "gpChange": 390, "loggedIn": "Yes", "notes": "", "logoutStreak": 0}, "a12TgDBqy3hFMqNeRU2MXyQa2sg1": {"name": "SnakieDLK", "oldGP": 21770, "newGP": 22170, "gpChange": 400, "loggedIn": "Yes", "notes": "", "logoutStreak": 0}, "af5tvJFlgGYc1sjAvxbeIquRY353": {"name": "Lolman14000", "oldGP": 15490, "newGP": 15880, "gpChange": 390, "loggedIn": "Yes", "notes": "", "logoutStreak": 0}, "b2dYxHgZqweNjVhmLAu3WiTLAG12": {"name": "kapiga", "oldGP": 7070, "newGP": 7330, "gpChange": 260, "loggedIn": "Yes", "notes": "", "logoutStreak": 0}, "bIcKjS7cKYTc0xbhwaEV4MFnbqB2": {"name": "Azfiel5", "oldGP": 14460, "newGP": 14940, "gpChange": 480, "loggedIn": "Yes", "notes": "", "logoutStreak": 0}, "c7SZMVXYBYWJqzoxdausTIhq5lx2": {"name": "Soraa46", "oldGP": 13060, "newGP": 13380, "gpChange": 320, "loggedIn": "Yes", "notes": "", "logoutStreak": 0}, "cB3Bkn1dFuXPLQhyrHL4DpcJEGe2": {"name": "Slave224", "oldGP": 15740, "newGP": 16130, "gpChange": 390, "loggedIn": "Yes", "notes": "", "logoutStreak": 0}, "ctv2aLD5b7OirIm5j4zuVaCQCRr1": {"name": "Fischious", "oldGP": 31138, "newGP": 31828, "gpChange": 690, "loggedIn": "Yes", "notes": "", "logoutStreak": 0}, "dULjoX0WhtceBuDBpuG75YSqrLo1": {"name": "C0deviper", "oldGP": 26590, "newGP": 27190, "gpChange": 600, "loggedIn": "Yes", "notes": "", "logoutStreak": 0}, "dWTH2yUt8VUBhESwGtpWX1sfGBJ2": {"name": "Bozimbo", "oldGP": 4830, "newGP": 5380, "gpChange": 550, "loggedIn": "Yes", "notes": "", "logoutStreak": 0}, "eM5vIHGO31RSd5mHBTH5X6xrxNk2": {"name": "Fujinnn", "oldGP": 4180, "newGP": 4670, "gpChange": 490, "loggedIn": "Yes", "notes": "", "logoutStreak": 0}, "eVTfAIPBSpS80QCb1maMw2GmwXI3": {"name": "JustAName2", "oldGP": 17640, "newGP": 17940, "gpChange": 300, "loggedIn": "Yes", "notes": "", "logoutStreak": 0}, "eyX9lEMtukfnhrI5sfINe2ncJf02": {"name": "Tepz6", "oldGP": 11240, "newGP": 11310, "gpChange": 70, "loggedIn": "Yes", "notes": "", "logoutStreak": 0}, "fK2UjGTZeygK5z6CErbSBsIfkL63": {"name": "Bahamut04", "oldGP": 13580, "newGP": 13790, "gpChange": 210, "loggedIn": "Yes", "notes": "", "logoutStreak": 0}, "fls2UnZy6aPA9pJs9bqCAtcxZpz1": {"name": "XIV_Warlord", "oldGP": 270, "newGP": 420, "gpChange": 150, "loggedIn": "Yes", "notes": "", "logoutStreak": 0}, "fnqFTQ19znekuES6YDAYLiUKcWr1": {"name": "ramoncuf7", "oldGP": 2420, "newGP": 2470, "gpChange": 50, "loggedIn": "Yes", "notes": "", "logoutStreak": 0}, "gBCXMHfKdwMEt3FqiV8zf8wktCh2": {"name": "Dootcom", "oldGP": 12950, "newGP": 13360, "gpChange": 410, "loggedIn": "Yes", "notes": "", "logoutStreak": 0}, "h0mmfuIyOnN4eDc7Rheks3bTeRq1": {"name": "GWillsJ", "oldGP": 27950, "newGP": 28410, "gpChange": 460, "loggedIn": "Yes", "notes": "", "logoutStreak": 0}, "h68XNIPhyNVfc6NBxeafo1Vn3Cv1": {"name": "KyoukaIz", "oldGP": 17380, "newGP": 17840, "gpChange": 460, "loggedIn": "Yes", "notes": "", "logoutStreak": 0}, "hR0KKaP4BGfOF7fPEei4gtJVI1Z2": {"name": "wither763", "oldGP": 9858, "newGP": 10148, "gpChange": 290, "loggedIn": "Yes", "notes": "", "logoutStreak": 0}, "hrsNscJfD3Tok0g1GTNHM2hQlch1": {"name": "Klozie", "oldGP": 17350, "newGP": 17750, "gpChange": 400, "loggedIn": "Yes", "notes": "", "logoutStreak": 0}, "iBDwTBH51IZ1rys20ZzHWC1HhGA2": {"name": "0ddish", "oldGP": 21200, "newGP": 21960, "gpChange": 760, "loggedIn": "Yes", "notes": "", "logoutStreak": 0}, "iN986fFEmZNzbepxpMkmHsYubRj2": {"name": "MaestroWreq", "oldGP": 8660, "newGP": 8660, "gpChange": 0, "loggedIn": "No", "notes": "", "logoutStreak": 1}, "jeremIm2lXQbixujf8ySIiCrllD2": {"name": "ImpuraGuts", "oldGP": 19070, "newGP": 19540, "gpChange": 470, "loggedIn": "Yes", "notes": "", "logoutStreak": 0}, "k2C6yHzDssU0pgKRTqD4YBXGn6z1": {"name": "petronum", "oldGP": 4410, "newGP": 4790, "gpChange": 380, "loggedIn": "Yes", "notes": "", "logoutStreak": 0}, "kSQN3XXRp7cE6yZ4lHdRJ40p9eo1": {"name": "MrWillie", "oldGP": 32790, "newGP": 33340, "gpChange": 550, "loggedIn": "Yes", "notes": "", "logoutStreak": 0}, "kiCHgjclquVyLn2uQLVzeEgjQf83": {"name": "Shwoosh", "oldGP": 15310, "newGP": 15690, "gpChange": 380, "loggedIn": "Yes", "notes": "", "logoutStreak": 0}, "ktRz0R0hW6VIKJ7NLTRFcMB9Z8V2": {"name": "TankXKD", "oldGP": 4600, "newGP": 5080, "gpChange": 480, "loggedIn": "Yes", "notes": "", "logoutStreak": 0}, "kuRgu4kNoPQrCg6lUyeMy3GS1zp2": {"name": "nazoth", "oldGP": 2100, "newGP": 2440, "gpChange": 340, "loggedIn": "Yes", "notes": "", "logoutStreak": 0}, "lGUY46VEYjYBp5JG6B3bMnNUVfZ2": {"name": "Sh4d0wz4", "oldGP": 0, "newGP": 110, "gpChange": 110, "loggedIn": "Yes", "notes": "New member", "logoutStreak": 0}, "lINTHJIhNWhJYgVGluby9tMt6tf2": {"name": "Jackobar", "oldGP": 15610, "newGP": 16180, "gpChange": 570, "loggedIn": "Yes", "notes": "", "logoutStreak": 0}, "ljPfEWFEnbaI64u5FaQQuxOf1J33": {"name": "Heknow", "oldGP": 17730, "newGP": 18090, "gpChange": 360, "loggedIn": "Yes", "notes": "", "logoutStreak": 0}, "mRn1dByTVXZc9Ub7gx3EfTnZx5K2": {"name": "Klorika", "oldGP": 17570, "newGP": 17980, "gpChange": 410, "loggedIn": "Yes", "notes": "", "logoutStreak": 0}, "mWxyIv2VlxgmvZD47bhoHI52tFD2": {"name": "YungToolyV5", "oldGP": 12990, "newGP": 13360, "gpChange": 370, "loggedIn": "Yes", "notes": "", "logoutStreak": 0}, "mdYgHLFTRnNDHtealkYJVOP01B72": {"name": "PrimarchYautja", "oldGP": 15200, "newGP": 15630, "gpChange": 430, "loggedIn": "Yes", "notes": "", "logoutStreak": 0}, "mhQtRvayEyg92XB7bHjuCg6qFTc2": {"name": "Entitsu", "oldGP": 3980, "newGP": 4460, "gpChange": 480, "loggedIn": "Yes", "notes": "", "logoutStreak": 0}, "mjD4IKkLOqMDNzyvAa3fqpMindw2": {"name": "1hitOneKill", "oldGP": 2690, "newGP": 2850, "gpChange": 160, "loggedIn": "Yes", "notes": "", "logoutStreak": 0}, "n2yJX35f6HVzLZQR5dHU2XdKU1s1": {"name": "qDarTz", "oldGP": 14980, "newGP": 15690, "gpChange": 710, "loggedIn": "Yes", "notes": "", "logoutStreak": 0}, "nFf3T2ztxmQ42qcBgo1Q6tqFjRA3": {"name": "Slitherpuff", "oldGP": 12540, "newGP": 13120, "gpChange": 580, "loggedIn": "Yes", "notes": "", "logoutStreak": 0}, "nhwfQDjGoPWKCxUcOqw1AvUXYmy2": {"name": "Sapprdedosio", "oldGP": 19850, "newGP": 20270, "gpChange": 420, "loggedIn": "Yes", "notes": "", "logoutStreak": 0}, "oOR3hxCwC3hnRuA4rAVv9ZGTIAF3": {"name": "barelyAlive", "oldGP": 3990, "newGP": 4420, "gpChange": 430, "loggedIn": "Yes", "notes": "Name change (Old name: Pladins)", "logoutStreak": 0}, "oYfm6VNp0NaQDhURxnc3TSPwefj2": {"name": "Witcher_D_Lycan", "oldGP": 4740, "newGP": 4980, "gpChange": 240, "loggedIn": "Yes", "notes": "", "logoutStreak": 0}, "okLnoSxbF8XRMv3fDk4wXzzwnb03": {"name": "bog_standards", "oldGP": 1120, "newGP": 1540, "gpChange": 420, "loggedIn": "Yes", "notes": "", "logoutStreak": 0}, "pQnsvLj22dZB2u3o23x6CrzKWjh2": {"name": "the_realrune", "oldGP": 1210, "newGP": 1680, "gpChange": 470, "loggedIn": "Yes", "notes": "", "logoutStreak": 0}, "pU6eU5DQVbPzm89Tgw1od637CO93": {"name": "Bufftros", "oldGP": 12830, "newGP": 13190, "gpChange": 360, "loggedIn": "Yes", "notes": "", "logoutStreak": 0}, "pnsNOVcYDKcwwY9NRRXWV0oEVQn2": {"name": "RawrxD92", "oldGP": 8880, "newGP": 9220, "gpChange": 340, "loggedIn": "Yes", "notes": "", "logoutStreak": 0}, "pph8jjUNcKQ05CGouYRCWH9W1Zo1": {"name": "AAAASCREAM", "oldGP": 15899, "newGP": 16219, "gpChange": 320, "loggedIn": "Yes", "notes": "", "logoutStreak": 0}, "qmHfeYu8IUTKTevxEHH8UgtfiUZ2": {"name": "MoDxRanger", "oldGP": 7650, "newGP": 8040, "gpChange": 390, "loggedIn": "Yes", "notes": "", "logoutStreak": 0}, "qs5pLZVZHDMn8RiFweLoCZVH72d2": {"name": "PotaTraps", "oldGP": 16629, "newGP": 17089, "gpChange": 460, "loggedIn": "Yes", "notes": "", "logoutStreak": 0}, "rAGM7fPXsdXCofA53a1w0okea8g1": {"name": "Belt_Yuri", "oldGP": 910, "newGP": 1310, "gpChange": 400, "loggedIn": "Yes", "notes": "", "logoutStreak": 0}, "rJnjU8IHCmficzzZ0Bq8iEnMKFA3": {"name": "dyqe4", "oldGP": 17950, "newGP": 18390, "gpChange": 440, "loggedIn": "Yes", "notes": "", "logoutStreak": 0}, "rYtLWDD3W2NC6js8dUbsg1VSsdu2": {"name": "theBigGUSTO", "oldGP": 13970, "newGP": 14280, "gpChange": 310, "loggedIn": "Yes", "notes": "", "logoutStreak": 0}, "rcDRE3d8hXVMmMCbnIBI4HJJGWS2": {"name": "Mankind2000", "oldGP": 2950, "newGP": 3270, "gpChange": 320, "loggedIn": "Yes", "notes": "", "logoutStreak": 0}, "sKG3RmnqWkSFULkYWSzkaZr7nvq1": {"name": "IGRHephaestus", "oldGP": 1190, "newGP": 1590, "gpChange": 400, "loggedIn": "Yes", "notes": "", "logoutStreak": 0}, "sOIl999bVBM0CAsChtMU4hCZQeC2": {"name": "yimothy5", "oldGP": 1200, "newGP": 1690, "gpChange": 490, "loggedIn": "Yes", "notes": "", "logoutStreak": 0}, "swu8UZHuWGQyD3BYhsayH8iqvbS2": {"name": "solozac", "oldGP": 15480, "newGP": 15850, "gpChange": 370, "loggedIn": "Yes", "notes": "", "logoutStreak": 0}, "tNq1uPdUAHgUenMv2cfnZtyMtmo2": {"name": "Exorcist4", "oldGP": 6170, "newGP": 6960, "gpChange": 790, "loggedIn": "Yes", "notes": "", "logoutStreak": 0}, "tmdpoNt4zFXXn6htAGATCdjThFh2": {"name": "purewave", "oldGP": 10150, "newGP": 10360, "gpChange": 210, "loggedIn": "Yes", "notes": "", "logoutStreak": 0}, "tuFxRvgG5bOQsae3SUjS7NfozJJ3": {"name": "smittydad", "oldGP": 19990, "newGP": 20350, "gpChange": 360, "loggedIn": "Yes", "notes": "", "logoutStreak": 0}, "uLbXGWQ7sbRKQue1R444L1ZpsYR2": {"name": "Prommermadl", "oldGP": 13170, "newGP": 13570, "gpChange": 400, "loggedIn": "Yes", "notes": "", "logoutStreak": 0}, "vbMGvkQgX7QiXLbXPWBBhH5IGfR2": {"name": "saikoru36", "oldGP": 0, "newGP": 430, "gpChange": 430, "loggedIn": "Yes", "notes": "New member", "logoutStreak": 0}, "vc8rW44cHpXzXxzftpxlmsvncpp1": {"name": "J_Doggz", "oldGP": 400, "newGP": 750, "gpChange": 350, "loggedIn": "Yes", "notes": "", "logoutStreak": 0}, "w4swFQ0h24aPYcaWDxgiep219CN2": {"name": "Junbus", "oldGP": 14500, "newGP": 14830, "gpChange": 330, "loggedIn": "Yes", "notes": "", "logoutStreak": 0}, "w6VXU3M1gza7KyMpwYUuWmE089m2": {"name": "logs23", "oldGP": 11000, "newGP": 11300, "gpChange": 300, "loggedIn": "Yes", "notes": "", "logoutStreak": 0}, "wDa3fhSu2yQQs5Y8o49Ug5hWzpu2": {"name": "jolebackins", "oldGP": 14820, "newGP": 14990, "gpChange": 170, "loggedIn": "Yes", "notes": "", "logoutStreak": 0}, "wQQqJpY9bYhC4JxHPucBi5EVjVj1": {"name": "BlackDogZep", "oldGP": 1600, "newGP": 2040, "gpChange": 440, "loggedIn": "Yes", "notes": "", "logoutStreak": 0}, "wkSGRLYUcBP9nyeyDLe0TG09Iap1": {"name": "StrakeFox", "oldGP": 14900, "newGP": 15410, "gpChange": 510, "loggedIn": "Yes", "notes": "", "logoutStreak": 0}, "wyx9v9L5HAO28yAYR9aQf3SBxRs2": {"name": "Nekoshimi", "oldGP": 27160, "newGP": 27570, "gpChange": 410, "loggedIn": "Yes", "notes": "", "logoutStreak": 0}, "x4zAG2W0roWYxMEZzjPQC2gRiGH2": {"name": "SirBigWhite2", "oldGP": 19280, "newGP": 19880, "gpChange": 600, "loggedIn": "Yes", "notes": "", "logoutStreak": 0}, "x9Tf42PDMvVFD1PvUISPFUrCFTG3": {"name": "anstrah", "oldGP": 28690, "newGP": 29620, "gpChange": 930, "loggedIn": "Yes", "notes": "", "logoutStreak": 0}, "xOrf6JhI1uR8IIl5aTjWIkw2vrB2": {"name": "Saintdane4", "oldGP": 16750, "newGP": 17180, "gpChange": 430, "loggedIn": "Yes", "notes": "", "logoutStreak": 0}, "xny2cOp3I9YQvOXdRLSW400Wdms2": {"name": "SaltyBanana", "oldGP": 1790, "newGP": 1970, "gpChange": 180, "loggedIn": "Yes", "notes": "", "logoutStreak": 0}, "xppC5jvhHCMtAxlbEiSetJvqb0t1": {"name": "Alexzphoenix", "oldGP": 20690, "newGP": 21510, "gpChange": 820, "loggedIn": "Yes", "notes": "", "logoutStreak": 0}, "yevhVIiuXtTJoGKLfP8kaX4eYFl1": {"name": "Donskeptic", "oldGP": 12060, "newGP": 12520, "gpChange": 460, "loggedIn": "Yes", "notes": "Name change (Old name: BerMalBerIst)", "logoutStreak": 0}, "z4IIORN8PVccA93jPWj8nlQWzDO2": {"name": "xKelevra", "oldGP": 6390, "newGP": 6860, "gpChange": 470, "loggedIn": "Yes", "notes": "", "logoutStreak": 0}, "zG22S7Ed90SfUE7wrTMpAO6Ec9D3": {"name": "Anderscore5", "oldGP": 4560, "newGP": 4820, "gpChange": 260, "loggedIn": "Yes", "notes": "", "logoutStreak": 0}, "zOWDSI50EZhfbZhfbyeDXrq6xHB3": {"name": "JJsmith", "oldGP": 7670, "newGP": 7940, "gpChange": 270, "loggedIn": "Yes", "notes": "", "logoutStreak": 0}, "zhYsbOtPCwYh3E7oX3O3ngDJ2NB2": {"name": "ItsZen", "oldGP": 13960, "newGP": 14420, "gpChange": 460, "loggedIn": "Yes", "notes": "", "logoutStreak": 0}, "zrO164g4bYhJELhdyHf4dL5V67w1": {"name": "Bruunchilda", "oldGP": 6480, "newGP": 6940, "gpChange": 460, "loggedIn": "Yes", "notes": "", "logoutStreak": 0}, "zvBPkOpg30Mepk7o1I9XWXJ8eIL2": {"name": "xamama", "oldGP": 9150, "newGP": 9370, "gpChange": 220, "loggedIn": "Yes", "notes": "", "logoutStreak": 0}, "0njVaRbWcpPMdrKGZy8pDq9yweH3": {"name": "Non_Existent", "oldGP": 3990, "newGP": 0, "gpChange": -3990, "loggedIn": "No", "notes": "Kicked or left the Guild o7", "logoutStreak": 0}, "D5pHUIpqGSamGq76HfUQeBzEBm33": {"name": "nicolas999", "oldGP": 2870, "newGP": 0, "gpChange": -2870, "loggedIn": "No", "notes": "Kicked or left the Guild o7", "logoutStreak": 0}, "Inpj1f8S7HXTFS5Q0cW2g5o3P9f1": {"name": "Jappie", "oldGP": 3930, "newGP": 0, "gpChange": -3930, "loggedIn": "No", "notes": "Kicked or left the Guild o7", "logoutStreak": 0}, "KlCzojtKBkcn1NXccqsSkAvlbVO2": {"name": "Crazywarr", "oldGP": 670, "newGP": 0, "gpChange": -670, "loggedIn": "No", "notes": "Kicked or left the Guild o7", "logoutStreak": 0}, "r7kJY8tJVEUh7A760VO1dk1xYw12": {"name": "stingdtc", "oldGP": 480, "newGP": 0, "gpChange": -480, "loggedIn": "No", "notes": "Kicked or left the Guild o7", "logoutStreak": 0}, "vT1x7sCUIaMxo5V20bz5U60kSap1": {"name": "Only_Pans", "oldGP": 230, "newGP": 0, "gpChange": -230, "loggedIn": "No", "notes": "Kicked or left the Guild o7", "logoutStreak": 0}, "y7KKTM7Sj3aOaJJm0adrUwfef553": {"name": "DFABLE", "oldGP": 250, "newGP": 0, "gpChange": -250, "loggedIn": "No", "notes": "Kicked or left the Guild o7", "logoutStreak": 0}, "zJ0eWoK3KQc5LQY18iakEwUoLgM2": {"name": "Geeerard", "oldGP": 2280, "newGP": 0, "gpChange": -2280, "loggedIn": "No", "notes": "Kicked or left the Guild o7", "logoutStreak": 0}, "zkNSXuyFakRrEVjkeByLgsjNLGA2": {"name": "goku_ssj9", "oldGP": 2780, "newGP": 0, "gpChange": -2780, "loggedIn": "No", "notes": "Kicked or left the Guild o7", "logoutStreak": 0}}, "t": "1708899264-1709505501"}