{"d": {"0e5PWjMFjPRxq7foPMT4m71oTor1": {"name": "Goofytimex", "oldGP": 6580, "newGP": 6950, "gpChange": 370, "loggedIn": "Yes", "notes": "", "logoutStreak": 0}, "0emGFmlsIdQ0piit41DlsNJgh6j1": {"name": "Eelethra", "oldGP": 27770, "newGP": 28130, "gpChange": 360, "loggedIn": "Yes", "notes": "", "logoutStreak": 0}, "0m9Zw31oTEN37h3Uj7loxHwnUIb2": {"name": "Slave872", "oldGP": 10430, "newGP": 10840, "gpChange": 410, "loggedIn": "Yes", "notes": "", "logoutStreak": 0}, "1B4DssjVfSSDWdbuyBXSDs3zAGs2": {"name": "killocotber", "oldGP": 19320, "newGP": 19650, "gpChange": 330, "loggedIn": "Yes", "notes": "", "logoutStreak": 0}, "1gfDlatpnXW78L6hsh1W7ty9ZfX2": {"name": "Rety2G", "oldGP": 22670, "newGP": 22960, "gpChange": 290, "loggedIn": "Yes", "notes": "", "logoutStreak": 0}, "1ne7REF1mDcESKgDEN5uAnJauRe2": {"name": "Luhione", "oldGP": 20850, "newGP": 21280, "gpChange": 430, "loggedIn": "Yes", "notes": "", "logoutStreak": 0}, "1xQkv9YqI3Y2WK0AzLD20U1r2XF3": {"name": "sharkyofficial", "oldGP": 13560, "newGP": 13940, "gpChange": 380, "loggedIn": "Yes", "notes": "", "logoutStreak": 0}, "24lMdUf38TRpQxTRnkjLzee55Xt1": {"name": "Psykzeus_96", "oldGP": 24120, "newGP": 24500, "gpChange": 380, "loggedIn": "Yes", "notes": "", "logoutStreak": 0}, "2JtzdxjqLFdcW4YIbLgiX8gi6rf1": {"name": "Mocsala", "oldGP": 48630, "newGP": 49020, "gpChange": 390, "loggedIn": "Yes", "notes": "", "logoutStreak": 0}, "2PwuXcOdZrMQTir1fTd8GXa3kOx2": {"name": "jesusnpalz", "oldGP": 48100, "newGP": 48520, "gpChange": 420, "loggedIn": "Yes", "notes": "", "logoutStreak": 0}, "2WjdwwgyYkOhiVITzZXRktUTtKf2": {"name": "here_Ilie", "oldGP": 10540, "newGP": 10750, "gpChange": 210, "loggedIn": "Yes", "notes": "", "logoutStreak": 0}, "47E8pRRI92WlqvtvBpk8WOlB5vm2": {"name": "DannyBMX", "oldGP": 39400, "newGP": 39720, "gpChange": 320, "loggedIn": "Yes", "notes": "", "logoutStreak": 0}, "5LYzW3UpyEQQAn9rCxZlOREVelO2": {"name": "TrollsterMine2", "oldGP": 10270, "newGP": 10660, "gpChange": 390, "loggedIn": "Yes", "notes": "", "logoutStreak": 0}, "5ShLMg6zaJP5467WbEB6AEK3Qfj1": {"name": "Goo_Lawd", "oldGP": 8020, "newGP": 8480, "gpChange": 460, "loggedIn": "Yes", "notes": "", "logoutStreak": 0}, "5gRi7zO4HSdGWYogWqOLRBxK9bn1": {"name": "SymPlayTon", "oldGP": 20310, "newGP": 20860, "gpChange": 550, "loggedIn": "Yes", "notes": "", "logoutStreak": 0}, "6bDmPeQ6cPM5ghfkQS1U2xaLh4f2": {"name": "Cleaver133_2", "oldGP": 69740, "newGP": 70420, "gpChange": 680, "loggedIn": "Yes", "notes": "Name change (Old name: Cleaver133_5)", "logoutStreak": 0}, "6i2yGOP3lZXBUquOJ1WSZInrmml1": {"name": "khjjsdhkjsdfjh", "oldGP": 6050, "newGP": 6260, "gpChange": 210, "loggedIn": "Yes", "notes": "", "logoutStreak": 0}, "6ppVffCRMJN7mFDXGAvrBDqtP942": {"name": "PseuDoppel", "oldGP": 13310, "newGP": 13770, "gpChange": 460, "loggedIn": "Yes", "notes": "", "logoutStreak": 0}, "6s8nBomzBmZ5eewWfVMJloOTSq33": {"name": "MAHAMEDABDALLA", "oldGP": 1160, "newGP": 1220, "gpChange": 60, "loggedIn": "Yes", "notes": "", "logoutStreak": 0}, "6szcdLyESXZTtl9HuvLyFxprwwl1": {"name": "buffRhio", "oldGP": 20820, "newGP": 21260, "gpChange": 440, "loggedIn": "Yes", "notes": "", "logoutStreak": 0}, "8X7wzuUzATV6QHbvpGMQX99Z6hF3": {"name": "Kage80", "oldGP": 40830, "newGP": 41180, "gpChange": 350, "loggedIn": "Yes", "notes": "", "logoutStreak": 0}, "96i9VgytkXZwwZ2nfdx9M2GUFkW2": {"name": "TonyShmoney", "oldGP": 27080, "newGP": 27150, "gpChange": 70, "loggedIn": "Yes", "notes": "", "logoutStreak": 0}, "9VFWOp7xY1V9XMJ4prkNugn4aso2": {"name": "Yuperhello", "oldGP": 13290, "newGP": 13760, "gpChange": 470, "loggedIn": "Yes", "notes": "", "logoutStreak": 0}, "9paqWJmW6YVYOkuIuJtUhtbfwIb2": {"name": "Raresasore", "oldGP": 12580, "newGP": 12920, "gpChange": 340, "loggedIn": "Yes", "notes": "", "logoutStreak": 0}, "9r6XVaXnc4SXgFuqCvogyuAxGUQ2": {"name": "UnixReal", "oldGP": 25870, "newGP": 26260, "gpChange": 390, "loggedIn": "Yes", "notes": "", "logoutStreak": 0}, "9u0fET9aIvds6mXE8M3MCcsWYfz2": {"name": "Mirjpeer", "oldGP": 4430, "newGP": 4720, "gpChange": 290, "loggedIn": "Yes", "notes": "", "logoutStreak": 0}, "9z3NTdunktSzbIyTtUkp9boxc4G2": {"name": "bufflordd", "oldGP": 17560, "newGP": 17770, "gpChange": 210, "loggedIn": "Yes", "notes": "", "logoutStreak": 0}, "AbwxAIHNKrRwG4QzsTOMLJMZ0k83": {"name": "Olivefarmer", "oldGP": 12900, "newGP": 13250, "gpChange": 350, "loggedIn": "Yes", "notes": "", "logoutStreak": 0}, "C8X3URsmwpV4Msmg2gJ9AcEFSGL2": {"name": "19funguy99", "oldGP": 770, "newGP": 1420, "gpChange": 650, "loggedIn": "Yes", "notes": "", "logoutStreak": 0}, "CEJKbf7WI5TSJVavoPdlRVYU8uy2": {"name": "Zwirrfinst8", "oldGP": 11070, "newGP": 11560, "gpChange": 490, "loggedIn": "Yes", "notes": "", "logoutStreak": 0}, "CgTldM68PJhQUuVd6JubIuYNqIj2": {"name": "hantomi", "oldGP": 31210, "newGP": 31480, "gpChange": 270, "loggedIn": "Yes", "notes": "", "logoutStreak": 0}, "CmAzbkESxlhd1dAuwxygClvQwEb2": {"name": "Dadoum", "oldGP": 13840, "newGP": 14070, "gpChange": 230, "loggedIn": "Yes", "notes": "", "logoutStreak": 0}, "DaF8JVUiY6Xh0q3SAKyXGNX82es1": {"name": "Shikamru", "oldGP": 26500, "newGP": 27180, "gpChange": 680, "loggedIn": "Yes", "notes": "", "logoutStreak": 0}, "DgPdNfOohcYbEewo5TKIVkWfZDD3": {"name": "Im_Skrud3", "oldGP": 36650, "newGP": 36890, "gpChange": 240, "loggedIn": "Yes", "notes": "", "logoutStreak": 0}, "DhnIut9EhKZzGlF9hTS7l5wTS062": {"name": "BrassBound", "oldGP": 15460, "newGP": 15820, "gpChange": 360, "loggedIn": "Yes", "notes": "", "logoutStreak": 0}, "DkaKnbPPLCZqRt5kTd3vRyBghsU2": {"name": "Pinodk", "oldGP": 4420, "newGP": 4850, "gpChange": 430, "loggedIn": "Yes", "notes": "", "logoutStreak": 0}, "Ds7AluNyemYXAQBY1BuDM1llQkv1": {"name": "Skluck", "oldGP": 14410, "newGP": 14690, "gpChange": 280, "loggedIn": "Yes", "notes": "", "logoutStreak": 0}, "EAfKQsLwlqdmgxGaqgD6Zu4C9MB3": {"name": "Zen_Man", "oldGP": 68220, "newGP": 68880, "gpChange": 660, "loggedIn": "Yes", "notes": "", "logoutStreak": 0}, "FYhAr8DloqNuKPGA7MPlega83WD3": {"name": "ArnoldBurger", "oldGP": 13330, "newGP": 13720, "gpChange": 390, "loggedIn": "Yes", "notes": "", "logoutStreak": 0}, "GPrxGoGPz2TWXnQOj1wpBvfDl8y2": {"name": "WizDeimos", "oldGP": 40580, "newGP": 40870, "gpChange": 290, "loggedIn": "Yes", "notes": "", "logoutStreak": 0}, "GW1vv0a6gOhcEBvFS6r4rBUkaPk2": {"name": "Tentacule", "oldGP": 19740, "newGP": 20120, "gpChange": 380, "loggedIn": "Yes", "notes": "", "logoutStreak": 0}, "H8u1euh8q5SdCFEiRbzYhmD8tO02": {"name": "ConfusedChemist", "oldGP": 160, "newGP": 260, "gpChange": 100, "loggedIn": "Yes", "notes": "", "logoutStreak": 0}, "HIng4OjXbbMggQgiCwiHuiuYC0q2": {"name": "Malibuhu", "oldGP": 24980, "newGP": 25370, "gpChange": 390, "loggedIn": "Yes", "notes": "", "logoutStreak": 0}, "HtRm8vqEgRYf7QUz52KNBjkXDMF3": {"name": "BAERGRILZ", "oldGP": 23420, "newGP": 23540, "gpChange": 120, "loggedIn": "Yes", "notes": "", "logoutStreak": 0}, "I4f3nhNgQ8QWAN8peR12uRHmR333": {"name": "nidosaur", "oldGP": 2480, "newGP": 2830, "gpChange": 350, "loggedIn": "Yes", "notes": "", "logoutStreak": 0}, "IBBzAhguBxWZBgnnr86b3UB3OhX2": {"name": "NameLessTD", "oldGP": 8250, "newGP": 8690, "gpChange": 440, "loggedIn": "Yes", "notes": "", "logoutStreak": 0}, "JEMmMroIwBfjB0e9KVwaDiHeulz2": {"name": "heesch", "oldGP": 31330, "newGP": 31330, "gpChange": 0, "loggedIn": "No", "notes": "", "logoutStreak": 1}, "JUwOJ5RM3cMdXi8RkUvpaimoRP43": {"name": "danilo3522", "oldGP": 25810, "newGP": 26220, "gpChange": 410, "loggedIn": "Yes", "notes": "", "logoutStreak": 0}, "JWpOSu4id8V5SpVdPUKrRn9Lxfy1": {"name": "lilabi", "oldGP": 14620, "newGP": 14960, "gpChange": 340, "loggedIn": "Yes", "notes": "", "logoutStreak": 0}, "JnXhwhsULacgtAMdFK1Gmx7TfPA3": {"name": "Darcushunter", "oldGP": 16630, "newGP": 16970, "gpChange": 340, "loggedIn": "Yes", "notes": "", "logoutStreak": 0}, "KAKSzNfxiFbFU3eBb2vxmuzM5F42": {"name": "4thonns", "oldGP": 14320, "newGP": 14700, "gpChange": 380, "loggedIn": "Yes", "notes": "", "logoutStreak": 0}, "KSjviymMRbeolAnHCOcaAxMD8gH2": {"name": "SoulsHawk", "oldGP": 460, "newGP": 1110, "gpChange": 650, "loggedIn": "Yes", "notes": "", "logoutStreak": 0}, "KVVOZxEMzvdknPcpcSFGeeZSzKV2": {"name": "FarmDoctor1", "oldGP": 16870, "newGP": 17110, "gpChange": 240, "loggedIn": "Yes", "notes": "", "logoutStreak": 0}, "KZD1KL7aV6f3yh7FZntIbQTpGhr2": {"name": "JJJSSSKKK", "oldGP": 27700, "newGP": 28080, "gpChange": 380, "loggedIn": "Yes", "notes": "", "logoutStreak": 0}, "KjfRyesLzETERomFyM5rGNLHvY92": {"name": "Khasos", "oldGP": 9920, "newGP": 9920, "gpChange": 0, "loggedIn": "No", "notes": "", "logoutStreak": 1}, "LBEmR89NCGOzIX4ZxCyXLl4Cwzm2": {"name": "Zaedin", "oldGP": 10130, "newGP": 10500, "gpChange": 370, "loggedIn": "Yes", "notes": "", "logoutStreak": 0}, "LQnhsiuQIlS1KIz7VrKbzWjmJh42": {"name": "Vayson", "oldGP": 63370, "newGP": 63870, "gpChange": 500, "loggedIn": "Yes", "notes": "", "logoutStreak": 0}, "LcHXedmcQTUFxgIKdduW6YGf2Zy2": {"name": "Crunshon", "oldGP": 30540, "newGP": 30920, "gpChange": 380, "loggedIn": "Yes", "notes": "", "logoutStreak": 0}, "LcdRwikbzpYuhqc9VPGJcGbCiiP2": {"name": "EveElement", "oldGP": 20530, "newGP": 20720, "gpChange": 190, "loggedIn": "Yes", "notes": "", "logoutStreak": 0}, "MQ09IKzVSSRVpBWduCofXnW2hDv2": {"name": "le_Trap", "oldGP": 30320, "newGP": 30710, "gpChange": 390, "loggedIn": "Yes", "notes": "", "logoutStreak": 0}, "MQqmxKELsfRePJpvyvoBeJZzH963": {"name": "bigtoii", "oldGP": 26160, "newGP": 26230, "gpChange": 70, "loggedIn": "Yes", "notes": "", "logoutStreak": 0}, "NfJ1JUkMjUOIhX8vUcfEMkzs6Hb2": {"name": "Tietank", "oldGP": 6410, "newGP": 6850, "gpChange": 440, "loggedIn": "Yes", "notes": "", "logoutStreak": 0}, "Nj4ITDDplHdECR0WvuENZrNkGCN2": {"name": "Saorii", "oldGP": 35080, "newGP": 35500, "gpChange": 420, "loggedIn": "Yes", "notes": "", "logoutStreak": 0}, "O2z2XBrjAZQBJeqPi5NHRwjM4k52": {"name": "lychia", "oldGP": 6690, "newGP": 7030, "gpChange": 340, "loggedIn": "Yes", "notes": "", "logoutStreak": 0}, "O6650P4IY9fK8Pj36uZlRSdwYDu1": {"name": "Jay7077", "oldGP": 5720, "newGP": 5720, "gpChange": 0, "loggedIn": "No", "notes": "", "logoutStreak": 1}, "O9D67MPfyXfzBKNerU6kHS7zb853": {"name": "Ritoryu_3", "oldGP": 13330, "newGP": 13720, "gpChange": 390, "loggedIn": "Yes", "notes": "", "logoutStreak": 0}, "OOFJ5ZWhJYWRwsXzHb0F8Ipjl3C2": {"name": "Littleoz4", "oldGP": 18440, "newGP": 18810, "gpChange": 370, "loggedIn": "Yes", "notes": "", "logoutStreak": 0}, "OcqitDQ1WZejOf5zFiGkRtm5NRc2": {"name": "QuantumUru", "oldGP": 22220, "newGP": 22340, "gpChange": 120, "loggedIn": "Yes", "notes": "", "logoutStreak": 0}, "P5lTN3lx1mb2BhINJewShuTggV52": {"name": "hmmm_yesss", "oldGP": 280, "newGP": 670, "gpChange": 390, "loggedIn": "Yes", "notes": "", "logoutStreak": 0}, "PYJ3tRVCUZSRTQzaVzbCbu0OQ7T2": {"name": "phapsulongbun", "oldGP": 16130, "newGP": 16510, "gpChange": 380, "loggedIn": "Yes", "notes": "", "logoutStreak": 0}, "PwkXTRAa9mdV2fT5Gy2JG0iKjkU2": {"name": "BabygirlTess", "oldGP": 24680, "newGP": 24710, "gpChange": 30, "loggedIn": "Yes", "notes": "", "logoutStreak": 0}, "Q7hkZP3WtafCmZhBPJQMhRgHQ6E3": {"name": "Kiiraiyukitari", "oldGP": 14560, "newGP": 14990, "gpChange": 430, "loggedIn": "Yes", "notes": "", "logoutStreak": 0}, "QpaTX0K94WYhGIWEoLNa5bi6MG83": {"name": "Loabobo", "oldGP": 39670, "newGP": 40000, "gpChange": 330, "loggedIn": "Yes", "notes": "", "logoutStreak": 0}, "Rj9ROeMA9TbXnIqJCg4fPh4oqK42": {"name": "Mikasanee", "oldGP": 49280, "newGP": 49790, "gpChange": 510, "loggedIn": "Yes", "notes": "", "logoutStreak": 0}, "S3g6tiakQpbxNbYzPpI30MGIzwD3": {"name": "domebencee", "oldGP": 34190, "newGP": 34510, "gpChange": 320, "loggedIn": "Yes", "notes": "", "logoutStreak": 0}, "SDkrkwza2gXZT03De1f4sDnvWwR2": {"name": "Bourne_Four", "oldGP": 10130, "newGP": 10540, "gpChange": 410, "loggedIn": "Yes", "notes": "", "logoutStreak": 0}, "TAc8eH1Mk0TEHER4bADteJYDLK92": {"name": "ricshrd", "oldGP": 17710, "newGP": 17860, "gpChange": 150, "loggedIn": "Yes", "notes": "", "logoutStreak": 0}, "Tg1R6V08IeNF2xevf0Q0owy4OyE2": {"name": "ScrubbleDuckies", "oldGP": 23520, "newGP": 23840, "gpChange": 320, "loggedIn": "Yes", "notes": "", "logoutStreak": 0}, "TiGFMHyXQ0exjewBwZeefyyGOKn1": {"name": "Fadebakaa", "oldGP": 130, "newGP": 520, "gpChange": 390, "loggedIn": "Yes", "notes": "", "logoutStreak": 0}, "TjgLoQzIKGUQVOak40rYgaoALke2": {"name": "journeylcuker", "oldGP": 31550, "newGP": 31970, "gpChange": 420, "loggedIn": "Yes", "notes": "", "logoutStreak": 0}, "UJoEpTFxGZecM7PM3rdv4H69eGv1": {"name": "Celden_Nc", "oldGP": 39450, "newGP": 39830, "gpChange": 380, "loggedIn": "Yes", "notes": "", "logoutStreak": 0}, "UukEx1BETIZ6EwCEhlVaqK3U8CU2": {"name": "Demoinho", "oldGP": 16890, "newGP": 17300, "gpChange": 410, "loggedIn": "Yes", "notes": "", "logoutStreak": 0}, "UvqR0Dlxv0g7E2dJoD1TYi9ODqC3": {"name": "AFWK", "oldGP": 5170, "newGP": 5540, "gpChange": 370, "loggedIn": "Yes", "notes": "", "logoutStreak": 0}, "V55uPL5Eqth4iikNSQ3lrYwjNF82": {"name": "Noskrispy5", "oldGP": 15850, "newGP": 16340, "gpChange": 490, "loggedIn": "Yes", "notes": "", "logoutStreak": 0}, "V7YvnSvWyJbeqXnMMZnqShPLyKf2": {"name": "tangoA2", "oldGP": 4760, "newGP": 5010, "gpChange": 250, "loggedIn": "Yes", "notes": "", "logoutStreak": 0}, "VJW82G4PIFa0AADoZ96qT60pvHY2": {"name": "baneblood", "oldGP": 11570, "newGP": 11980, "gpChange": 410, "loggedIn": "Yes", "notes": "", "logoutStreak": 0}, "Vi6ck2yQhacFgDzVU1YeDeR3Onv1": {"name": "Happensmaker", "oldGP": 64050, "newGP": 64750, "gpChange": 700, "loggedIn": "Yes", "notes": "", "logoutStreak": 0}, "W722oXzeixffboAvUYBLwxdAUot2": {"name": "Lithinz", "oldGP": 54780, "newGP": 54940, "gpChange": 160, "loggedIn": "Yes", "notes": "", "logoutStreak": 0}, "WFe5JCgPoMV532ORzxSkrN2S7J43": {"name": "jibburJack", "oldGP": 32300, "newGP": 32660, "gpChange": 360, "loggedIn": "Yes", "notes": "", "logoutStreak": 0}, "WG7fXedlZYWIlb1poy3gFPakaLr2": {"name": "Lushcko", "oldGP": 29320, "newGP": 29750, "gpChange": 430, "loggedIn": "Yes", "notes": "", "logoutStreak": 0}, "WYI00ZR1cvVJUgsqz9fEIgs7EFH2": {"name": "mioeira", "oldGP": 8600, "newGP": 8970, "gpChange": 370, "loggedIn": "Yes", "notes": "", "logoutStreak": 0}, "Wkj7vOqPd0TgvOiXlKJFjldey6C2": {"name": "gooping", "oldGP": 6890, "newGP": 7030, "gpChange": 140, "loggedIn": "Yes", "notes": "", "logoutStreak": 0}, "WlqtfYYaXBRWWF9VzkxXBVKeNl52": {"name": "chalky123", "oldGP": 33740, "newGP": 34120, "gpChange": 380, "loggedIn": "Yes", "notes": "", "logoutStreak": 0}, "WlxM8GZbf3bwV57NxU7n6iWU1cL2": {"name": "Mayor15", "oldGP": 14170, "newGP": 14580, "gpChange": 410, "loggedIn": "Yes", "notes": "", "logoutStreak": 0}, "WvWcAB2AaneaBxZPti2e1olJfbo2": {"name": "Curse_OfThe", "oldGP": 5570, "newGP": 5920, "gpChange": 350, "loggedIn": "Yes", "notes": "", "logoutStreak": 0}, "X6ztcT9tDwhcE3ClHIMgkmHZ54n2": {"name": "Wharmy", "oldGP": 15210, "newGP": 15540, "gpChange": 330, "loggedIn": "Yes", "notes": "", "logoutStreak": 0}, "XiqpaARdDAQgka6JMKNVH0v0Zkm1": {"name": "wafflemf", "oldGP": 32000, "newGP": 32370, "gpChange": 370, "loggedIn": "Yes", "notes": "", "logoutStreak": 0}, "YDWdEe6Xf8akZ6xPzW0b1vcNyIn2": {"name": "Serkrem", "oldGP": 25980, "newGP": 26300, "gpChange": 320, "loggedIn": "Yes", "notes": "", "logoutStreak": 0}, "Yf35z2HWIuNF2USQK6IZUrLOhOp1": {"name": "Haenor", "oldGP": 19370, "newGP": 19800, "gpChange": 430, "loggedIn": "Yes", "notes": "", "logoutStreak": 0}, "YjLicoeBXLN4diop4TshiiEzJD12": {"name": "Dimie2", "oldGP": 18450, "newGP": 18820, "gpChange": 370, "loggedIn": "Yes", "notes": "", "logoutStreak": 0}, "Znygt7mo0gZmfaWaGFyxCx4GKWM2": {"name": "wicio54", "oldGP": 12390, "newGP": 12770, "gpChange": 380, "loggedIn": "Yes", "notes": "", "logoutStreak": 0}, "ZsnGoMIfQ9XnUvjcsq8hsCGuMC52": {"name": "smistsillythe3", "oldGP": 1540, "newGP": 1850, "gpChange": 310, "loggedIn": "Yes", "notes": "", "logoutStreak": 0}, "ZtndEtpASbOILloaY9Tx6h3ZkYi1": {"name": "EcknockBuff_guy", "oldGP": 7580, "newGP": 7580, "gpChange": 0, "loggedIn": "No", "notes": "", "logoutStreak": 1}, "ZwaSrypp0ibEFN2JG6cEaipqXa13": {"name": "SoggyBallz", "oldGP": 11770, "newGP": 12170, "gpChange": 400, "loggedIn": "Yes", "notes": "", "logoutStreak": 0}, "ahHs2urWaMMAiYAnc0aMtXaQl653": {"name": "omenuk", "oldGP": 30210, "newGP": 30540, "gpChange": 330, "loggedIn": "Yes", "notes": "", "logoutStreak": 0}, "am56am0rWKRmgkpmLQqRUkFk7hz1": {"name": "luckylouz", "oldGP": 5690, "newGP": 6020, "gpChange": 330, "loggedIn": "Yes", "notes": "", "logoutStreak": 0}, "b8oQPh0eX1NMbsmNh8R7lsJTI412": {"name": "J1g15Jag", "oldGP": 57970, "newGP": 58490, "gpChange": 520, "loggedIn": "Yes", "notes": "", "logoutStreak": 0}, "bJ0E94hAHMSPPSzTNuvlAZEXmRt2": {"name": "Serraaaaa", "oldGP": 1320, "newGP": 1670, "gpChange": 350, "loggedIn": "Yes", "notes": "", "logoutStreak": 0}, "bMCipgWju8UrOTtlUj1pbFYzMo03": {"name": "RattlyCheese44", "oldGP": 7290, "newGP": 7380, "gpChange": 90, "loggedIn": "Yes", "notes": "", "logoutStreak": 0}, "cBUaRkLWr5PSeEqf53lXsTJrO2n2": {"name": "Valiis", "oldGP": 30380, "newGP": 30810, "gpChange": 430, "loggedIn": "Yes", "notes": "", "logoutStreak": 0}, "cJRKGOf19YSgsnKFvp9upjff3xm2": {"name": "DiscordTurtle", "oldGP": 5030, "newGP": 5330, "gpChange": 300, "loggedIn": "Yes", "notes": "", "logoutStreak": 0}, "cWtHDohqwpcTNnOIoj6gnNoVncP2": {"name": "Pzor", "oldGP": 150, "newGP": 150, "gpChange": 0, "loggedIn": "No", "notes": "", "logoutStreak": 1}, "chabX8D1HBRJxbGjXCFsVfXLN9U2": {"name": "harborym", "oldGP": 16680, "newGP": 17020, "gpChange": 340, "loggedIn": "Yes", "notes": "", "logoutStreak": 0}, "cks8dPTdZRMJnZXp6J7seAovHbc2": {"name": "blueish1", "oldGP": 32120, "newGP": 32420, "gpChange": 300, "loggedIn": "Yes", "notes": "", "logoutStreak": 0}, "dEBQgdlpc8ObR1M1XWZCZSabo783": {"name": "Monadocyclone", "oldGP": 34050, "newGP": 34320, "gpChange": 270, "loggedIn": "Yes", "notes": "", "logoutStreak": 0}, "e1EB5KkuhpgPYblaJ2L6oaflMB72": {"name": "Msflexible", "oldGP": 44770, "newGP": 45100, "gpChange": 330, "loggedIn": "Yes", "notes": "", "logoutStreak": 0}, "eMkg3RpzSxfrtCALwzJBubtlCJg2": {"name": "zero61994", "oldGP": 37080, "newGP": 37490, "gpChange": 410, "loggedIn": "Yes", "notes": "", "logoutStreak": 0}, "ed7Qqa6BAsR1YNTbsgXaVl3uj6A2": {"name": "Rendlawsc", "oldGP": 30470, "newGP": 30820, "gpChange": 350, "loggedIn": "Yes", "notes": "", "logoutStreak": 0}, "efMkrd7mygWeVKy1noYrQ98kQM33": {"name": "superbam", "oldGP": 31730, "newGP": 32070, "gpChange": 340, "loggedIn": "Yes", "notes": "", "logoutStreak": 0}, "egAyhcwg9wajMqImGRHL3KAvt7D3": {"name": "stupidmonke", "oldGP": 3820, "newGP": 3880, "gpChange": 60, "loggedIn": "Yes", "notes": "", "logoutStreak": 0}, "emMCUwC4O5Wh2ZZu3E3FbleCW0v1": {"name": "Nexteron", "oldGP": 23470, "newGP": 23660, "gpChange": 190, "loggedIn": "Yes", "notes": "", "logoutStreak": 0}, "fFjh5hnbBHbWiTbRrP6TAVNravH2": {"name": "DarkExecute", "oldGP": 30230, "newGP": 30630, "gpChange": 400, "loggedIn": "Yes", "notes": "", "logoutStreak": 0}, "ffHNxoc2YSQBlSCBQU9BL70HyNy1": {"name": "G04tL33O", "oldGP": 22730, "newGP": 23130, "gpChange": 400, "loggedIn": "Yes", "notes": "", "logoutStreak": 0}, "fpfnj76uCVVkFtg76rrXXyXHfef2": {"name": "mgmasteroz", "oldGP": 19270, "newGP": 19270, "gpChange": 0, "loggedIn": "No", "notes": "", "logoutStreak": 1}, "fryL1nnOb4eT4VVtGk7xoC9wLrp1": {"name": "Mathias008", "oldGP": 16440, "newGP": 16830, "gpChange": 390, "loggedIn": "Yes", "notes": "", "logoutStreak": 0}, "g6zygPS7ccQWIFhZTh48Gqm7YgG2": {"name": "kaugoma6", "oldGP": 52240, "newGP": 52820, "gpChange": 580, "loggedIn": "Yes", "notes": "", "logoutStreak": 0}, "hjURMZMYUugKHhMHcVSZYuOZJ8g1": {"name": "Szesz", "oldGP": 10970, "newGP": 11010, "gpChange": 40, "loggedIn": "Yes", "notes": "", "logoutStreak": 0}, "hlUrihkPtHOZFoe4ZwVDYzOK4pL2": {"name": "UnblessedShield", "oldGP": 13790, "newGP": 14210, "gpChange": 420, "loggedIn": "Yes", "notes": "", "logoutStreak": 0}, "i51o79r4sweBoHSzp777ufD8gtw1": {"name": "the_brown_eye", "oldGP": 21880, "newGP": 22060, "gpChange": 180, "loggedIn": "Yes", "notes": "", "logoutStreak": 0}, "isTe3Rntitbc6uhpmEBS9bMsbjx2": {"name": "Ghoul_Official", "oldGP": 19900, "newGP": 20330, "gpChange": 430, "loggedIn": "Yes", "notes": "", "logoutStreak": 0}, "j1farE4OUwSuJAz2OSPDXqcnmZ02": {"name": "ZzGODzZ", "oldGP": 11750, "newGP": 12070, "gpChange": 320, "loggedIn": "Yes", "notes": "", "logoutStreak": 0}, "jLa0RRngvNeJy7mCL2O7dfyfFc93": {"name": "CakeShaman", "oldGP": 39620, "newGP": 39870, "gpChange": 250, "loggedIn": "Yes", "notes": "", "logoutStreak": 0}, "jpKfGdub2yN71bL3CvNXKjA7P4f2": {"name": "Jorna", "oldGP": 35110, "newGP": 35470, "gpChange": 360, "loggedIn": "Yes", "notes": "", "logoutStreak": 0}, "jwi5LGbF8JTVsdNiWaQt9Nu6Dng1": {"name": "waalliiee", "oldGP": 15620, "newGP": 15920, "gpChange": 300, "loggedIn": "Yes", "notes": "", "logoutStreak": 0}, "k8kF1fT85HbzqK6S0X7CqJVVlt12": {"name": "dolan22", "oldGP": 10180, "newGP": 10680, "gpChange": 500, "loggedIn": "Yes", "notes": "", "logoutStreak": 0}, "kAvlEv34BvdeaDNH0JRbmsjUqX33": {"name": "VerticalTacco", "oldGP": 16300, "newGP": 16630, "gpChange": 330, "loggedIn": "Yes", "notes": "", "logoutStreak": 0}, "kIDK8hjcKwadsBrVLpN5g91GWMs1": {"name": "veganesb12", "oldGP": 50350, "newGP": 50690, "gpChange": 340, "loggedIn": "Yes", "notes": "", "logoutStreak": 0}, "kUbJw1ppS3bPTZVyH9epzkkBKZN2": {"name": "dankuray", "oldGP": 36070, "newGP": 36360, "gpChange": 290, "loggedIn": "Yes", "notes": "", "logoutStreak": 0}, "kV6nRqv6juZ665FFrkvWynNVjNR2": {"name": "KOYOW", "oldGP": 25540, "newGP": 25880, "gpChange": 340, "loggedIn": "Yes", "notes": "", "logoutStreak": 0}, "katydzoxh1eFhwIhTAyfunsaq0S2": {"name": "hippo_crite", "oldGP": 34290, "newGP": 34670, "gpChange": 380, "loggedIn": "Yes", "notes": "", "logoutStreak": 0}, "kcBQkwhOwBQnSz3NNv1d8nIqftH3": {"name": "chicken_marsal", "oldGP": 29340, "newGP": 29750, "gpChange": 410, "loggedIn": "Yes", "notes": "", "logoutStreak": 0}, "kkRh3aVDUXZsaYLC7OdWhc9VJYE3": {"name": "Siviliana", "oldGP": 42960, "newGP": 43360, "gpChange": 400, "loggedIn": "Yes", "notes": "", "logoutStreak": 0}, "liKjbYcQBPgWDo4rwVcsRQZ0UmB3": {"name": "Froschn", "oldGP": 20950, "newGP": 21160, "gpChange": 210, "loggedIn": "Yes", "notes": "", "logoutStreak": 0}, "lxX3R3X3ajgXRHrtXlSMjb2Sjw62": {"name": "Big_smash", "oldGP": 13460, "newGP": 13780, "gpChange": 320, "loggedIn": "Yes", "notes": "", "logoutStreak": 0}, "m0qDFOhYqZe3NJXOTYkKDm4ZdWV2": {"name": "lukesiw", "oldGP": 15530, "newGP": 15990, "gpChange": 460, "loggedIn": "Yes", "notes": "", "logoutStreak": 0}, "mHmHW2sPx2NZ7GSM1OPktC8exMx1": {"name": "05Striker06", "oldGP": 23130, "newGP": 23490, "gpChange": 360, "loggedIn": "Yes", "notes": "", "logoutStreak": 0}, "mdYgHLFTRnNDHtealkYJVOP01B72": {"name": "PrimarchYautja", "oldGP": 13550, "newGP": 13960, "gpChange": 410, "loggedIn": "Yes", "notes": "", "logoutStreak": 0}, "medoQBKZxfcauTWtx5G48eTZufF2": {"name": "hempamin", "oldGP": 38440, "newGP": 38850, "gpChange": 410, "loggedIn": "Yes", "notes": "", "logoutStreak": 0}, "mhhYTwmXcEgJovDzABHRJrCN5Zg1": {"name": "grunnar", "oldGP": 28790, "newGP": 29000, "gpChange": 210, "loggedIn": "Yes", "notes": "", "logoutStreak": 0}, "mof0ANXtLZVPQ5HxwBSsHBWsOp23": {"name": "Marinxar", "oldGP": 6730, "newGP": 7130, "gpChange": 400, "loggedIn": "Yes", "notes": "", "logoutStreak": 0}, "nWv5opbYzYg4aUzt2sco9gESGjn2": {"name": "Riona_Owl", "oldGP": 6700, "newGP": 6700, "gpChange": 0, "loggedIn": "No", "notes": "", "logoutStreak": 1}, "nuEku14PLOMHXEnbzKCZV2QeYP32": {"name": "Ebtanta", "oldGP": 15660, "newGP": 16030, "gpChange": 370, "loggedIn": "Yes", "notes": "", "logoutStreak": 0}, "nvwzDQOA4CfijA4ujr2o37yWhgH3": {"name": "MistyczneDrzewo", "oldGP": 8920, "newGP": 9080, "gpChange": 160, "loggedIn": "Yes", "notes": "", "logoutStreak": 0}, "oTicKTfPH6X8sQ4DXvVXklatU1A3": {"name": "Wartor", "oldGP": 17820, "newGP": 18230, "gpChange": 410, "loggedIn": "Yes", "notes": "", "logoutStreak": 0}, "oXjAQeAyW4R2LeIJpiSSYanHKVw1": {"name": "SlayingMantis", "oldGP": 9000, "newGP": 9310, "gpChange": 310, "loggedIn": "Yes", "notes": "", "logoutStreak": 0}, "osqQU49oO5VQlcfD4F68Ghh4Wqs2": {"name": "Toftern", "oldGP": 21330, "newGP": 21730, "gpChange": 400, "loggedIn": "Yes", "notes": "", "logoutStreak": 0}, "oxSG9jBg8yal0FXNWXmAgiBVggC2": {"name": "badnews33", "oldGP": 19220, "newGP": 19450, "gpChange": 230, "loggedIn": "Yes", "notes": "", "logoutStreak": 0}, "p8OBCb6NQxcYm7AP6c5LvAEfXWG3": {"name": "TempestPika", "oldGP": 11710, "newGP": 11850, "gpChange": 140, "loggedIn": "Yes", "notes": "", "logoutStreak": 0}, "qNQJTqa7lravcj8AWdjbO9hURfN2": {"name": "Zialll", "oldGP": 12270, "newGP": 12420, "gpChange": 150, "loggedIn": "Yes", "notes": "", "logoutStreak": 0}, "qv62o7OGXVbSGComZ0nad9CjJ8r2": {"name": "net1", "oldGP": 21870, "newGP": 21960, "gpChange": 90, "loggedIn": "Yes", "notes": "", "logoutStreak": 0}, "r7SDYl61yROFDWbqPwnEWYV80tq2": {"name": "Paston_Skittal", "oldGP": 11490, "newGP": 11800, "gpChange": 310, "loggedIn": "Yes", "notes": "", "logoutStreak": 0}, "rFdQWJZFP3PvZnnAXIzitPX9uLi1": {"name": "Sp1C", "oldGP": 22150, "newGP": 22530, "gpChange": 380, "loggedIn": "Yes", "notes": "", "logoutStreak": 0}, "rWtW4StpWNNiR6bq2lpFA89gAok1": {"name": "Fontora", "oldGP": 6550, "newGP": 7040, "gpChange": 490, "loggedIn": "Yes", "notes": "", "logoutStreak": 0}, "rdAfFHFstuPzq3cUbXZ0UH9Zq0m2": {"name": "Nehta", "oldGP": 38530, "newGP": 38930, "gpChange": 400, "loggedIn": "Yes", "notes": "", "logoutStreak": 0}, "rdtRUZ6jQQSSLhfAVbA6FQ4SC0l2": {"name": "KoRnMAN711", "oldGP": 26760, "newGP": 27170, "gpChange": 410, "loggedIn": "Yes", "notes": "", "logoutStreak": 0}, "s5QI4nqBxdVQLGmPuEDw3c8UngA2": {"name": "Bambiim", "oldGP": 11230, "newGP": 11630, "gpChange": 400, "loggedIn": "Yes", "notes": "", "logoutStreak": 0}, "s9svRly1StbfqZrtpsqMWBcvmzF3": {"name": "GuitarNinja", "oldGP": 34920, "newGP": 35300, "gpChange": 380, "loggedIn": "Yes", "notes": "", "logoutStreak": 0}, "sFXq2kYXaZTuGyyUBv5YOGr6ceB2": {"name": "Chegzlife", "oldGP": 12960, "newGP": 13170, "gpChange": 210, "loggedIn": "Yes", "notes": "", "logoutStreak": 0}, "steam_76561198095757862": {"name": "magostat", "oldGP": 1950, "newGP": 2500, "gpChange": 550, "loggedIn": "Yes", "notes": "", "logoutStreak": 0}, "steam_76561198171606214": {"name": "Bubosu", "oldGP": 1480, "newGP": 1960, "gpChange": 480, "loggedIn": "Yes", "notes": "", "logoutStreak": 0}, "steam_76561198341943180": {"name": "QingShan_Gu", "oldGP": 580, "newGP": 1020, "gpChange": 440, "loggedIn": "Yes", "notes": "", "logoutStreak": 0}, "steam_76561198356099213": {"name": "mifa1", "oldGP": 470, "newGP": 920, "gpChange": 450, "loggedIn": "Yes", "notes": "", "logoutStreak": 0}, "steam_76561199756936150": {"name": "neiyhihga", "oldGP": 840, "newGP": 1240, "gpChange": 400, "loggedIn": "Yes", "notes": "", "logoutStreak": 0}, "t4fbrh15PBQcMTz37CDen0V7p0a2": {"name": "SaninTea", "oldGP": 38180, "newGP": 38540, "gpChange": 360, "loggedIn": "Yes", "notes": "", "logoutStreak": 0}, "uOtzORx8iZcoiNnfiyrHziCbxus1": {"name": "SUGOMAGUY", "oldGP": 28160, "newGP": 28160, "gpChange": 0, "loggedIn": "No", "notes": "", "logoutStreak": 1}, "ucw43rep0JRO3qMjqBQfPw3Lh6v2": {"name": "Aevynh", "oldGP": 40210, "newGP": 40610, "gpChange": 400, "loggedIn": "Yes", "notes": "", "logoutStreak": 0}, "vBQNss5z7tOFHpEA0ZqrMYfFt4n1": {"name": "Wis3ly", "oldGP": 31910, "newGP": 32470, "gpChange": 560, "loggedIn": "Yes", "notes": "", "logoutStreak": 0}, "vp9IvcQf1dZ4sHYJOMkLcPO3F8P2": {"name": "Yuf1", "oldGP": 1240, "newGP": 1600, "gpChange": 360, "loggedIn": "Yes", "notes": "", "logoutStreak": 0}, "w4tCyLbPzuc0p8oWG5wz8JlF6nx1": {"name": "Lenn3", "oldGP": 7360, "newGP": 7760, "gpChange": 400, "loggedIn": "Yes", "notes": "", "logoutStreak": 0}, "wsl3hl0n3uRnkr08RkB2atrmL1h1": {"name": "Warrior_Dorian", "oldGP": 160, "newGP": 520, "gpChange": 360, "loggedIn": "Yes", "notes": "", "logoutStreak": 0}, "xOd8rycABIN6o7YLHWCEC2DNR2t1": {"name": "Psy_Craft", "oldGP": 19960, "newGP": 20230, "gpChange": 270, "loggedIn": "Yes", "notes": "", "logoutStreak": 0}, "xnPi6BmwoMSYPr7EVWTumKINOa83": {"name": "Gomaa", "oldGP": 37250, "newGP": 37600, "gpChange": 350, "loggedIn": "Yes", "notes": "", "logoutStreak": 0}, "xpgVwfTERnPUZ6c15JNdnAzcWl53": {"name": "omnji", "oldGP": 39060, "newGP": 39440, "gpChange": 380, "loggedIn": "Yes", "notes": "", "logoutStreak": 0}, "y913pSSumEZA8LcjpEsbGn8yOfu2": {"name": "zeagon", "oldGP": 30230, "newGP": 30410, "gpChange": 180, "loggedIn": "Yes", "notes": "", "logoutStreak": 0}, "z3nXqjFoxxWwSHgZv21f8XA6eC82": {"name": "Tylenoltim", "oldGP": 4610, "newGP": 4910, "gpChange": 300, "loggedIn": "Yes", "notes": "", "logoutStreak": 0}, "zL6RhthMNjaazMLMOagH268rhez1": {"name": "staubera", "oldGP": 17970, "newGP": 18240, "gpChange": 270, "loggedIn": "Yes", "notes": "", "logoutStreak": 0}, "zNqyZYotFZRWOLmCAfb4onPSbh02": {"name": "antranig", "oldGP": 21480, "newGP": 21810, "gpChange": 330, "loggedIn": "Yes", "notes": "", "logoutStreak": 0}}, "t": "1750021203-1750626254"}