{"d": {"0r8GKGX957Y4Gn3oS4Va9Uzcm7H3": {"a": "Voxtin", "b": "", "c": 22, "d": 1241, "e": 7870, "f": 17, "g": 2, "joinTimestamp": 1764540021, "knownNames": ["Voxtin"], "logoutStreak": 0}, "12VVeY2cL9X19oyfEyOF6Q7SV933": {"a": "ThePyroagain", "b": "", "c": 29, "d": 1444, "e": 52440, "f": 17, "g": 2, "joinTimestamp": 1717969353, "knownNames": ["ThePyroMain", "ThePyroagain"], "logoutStreak": 0}, "13KiHyI5W5fVNIg3Xx9sMsYUngo1": {"a": "BlindLITE", "b": "", "c": 14, "d": 1037, "e": 2880, "f": -1, "g": 2, "joinTimestamp": 1769983458, "knownNames": ["BlindLITE"], "logoutStreak": 0}, "16D6wPspnab14GsOe6qYdnO2k4Q2": {"a": "Nrogeth2", "b": "", "c": 40, "d": 1136, "e": 53700, "f": 17, "g": 2, "joinTimestamp": 1690384492, "knownNames": ["Nrogeth2"], "logoutStreak": 0}, "1QqAP8mDPRMrae74Xi2UUtFhoOu2": {"a": "jamonz", "b": "", "c": 14, "d": 1000, "e": 46330, "f": 10, "g": 2, "joinTimestamp": 1690384492, "knownNames": ["jamonz"], "logoutStreak": 0}, "1j01Zm8LJ2h1DUTawCxgZxJrS7w1": {"a": "ReinaTeri", "b": "", "c": 12, "d": 1502, "e": 36610, "f": 17, "g": 2, "joinTimestamp": 1726434226, "knownNames": ["LadyTeri", "MoniTeri", "ReinaTeri"], "logoutStreak": 0}, "1lEbP3HiVMZ7IFmADuFVS3qRoCr2": {"a": "Adriano_Zoxul", "b": "", "c": 4, "d": 1209, "e": 71020, "f": 10, "g": 2, "joinTimestamp": 1690384492, "knownNames": ["Adriano_Zoxul"], "logoutStreak": 0}, "1uCNHrrF5pUqN9Z707PleA7uE8L2": {"a": "mithaaahh", "b": "", "c": 22, "d": 1410, "e": 52070, "f": -1, "g": 2, "joinTimestamp": 1690384492, "knownNames": ["mithaaahh"], "logoutStreak": 0}, "2OblnVihkPNOtuNt9uhN1nKUCbw1": {"a": "Grid", "b": "", "c": 12, "d": 1359, "e": 18790, "f": 17, "g": 2, "joinTimestamp": 1730671402, "knownNames": ["Quasi", "Grid"], "logoutStreak": 0}, "2y8ANxEKQsTB9qTnmSqfznB1NXo2": {"a": "MortSith", "b": "", "c": 34, "d": 1310, "e": 38990, "f": 17, "g": 2, "joinTimestamp": 1712524012, "knownNames": ["MortSith"], "logoutStreak": 0}, "38hHEcAXltcOvuJijpi6gSI8gYj2": {"a": "Poopsterr", "b": "", "c": 12, "d": 1429, "e": 38800, "f": 14, "g": 2, "joinTimestamp": 1720991370, "knownNames": ["Poopsterr"], "logoutStreak": 0}, "3WGspJRYHbOte3uu9f16u5CnkIH3": {"a": "WadeWilson98", "b": "", "c": 22, "d": 786, "e": 43110, "f": 5, "g": 2, "joinTimestamp": 1690384492, "knownNames": ["WadeWilson98"], "logoutStreak": 0}, "3rtwdTiQijg5WQaneiPUTyRQu3H3": {"a": "imfluffy", "b": "", "c": 40, "d": 1305, "e": 22970, "f": 17, "g": 2, "joinTimestamp": 1737324013, "knownNames": ["imfluffy"], "logoutStreak": 0}, "41wr8KuHOcfLu7ys4OS9NAAOQff1": {"a": "Pikels", "b": "", "c": 14, "d": 1163, "e": 61156, "f": -1, "g": 2, "joinTimestamp": 1690384492, "knownNames": ["Pikels"], "logoutStreak": 0}, "4AiQigK49khm16prBa9yqKx8ySC3": {"a": "Minexx", "b": "", "c": 14, "d": 928, "e": 50930, "f": 0, "g": 2, "joinTimestamp": 1690384492, "knownNames": ["Minexx"], "logoutStreak": 0}, "4LyhLS2OahaH24mgCRPLRTFoJz62": {"a": "callybrewntrbl", "b": "", "c": 40, "d": 1441, "e": 76280, "f": 17, "g": 2, "joinTimestamp": 1690384492, "knownNames": ["callythearchy", "callythewizzy", "callybrewntrbl"], "logoutStreak": 0}, "4S5k99Y7VLSehLOEHaihGjzisFU2": {"a": "Xandic", "b": "", "c": 14, "d": 989, "e": 27070, "f": -1, "g": 2, "joinTimestamp": 1730671402, "knownNames": ["Xandic"], "logoutStreak": 0}, "4SLsmdvqu9hfmnldo9luQMS3zDi2": {"a": "Varsixli", "b": "", "c": 14, "d": 1173, "e": 63220, "f": 17, "g": 2, "joinTimestamp": 1690384492, "knownNames": ["Varsixli"], "logoutStreak": 0}, "4mCbEJ92wjT7Y2R1SBPu8LELIky2": {"a": "forsenmods", "b": "", "c": 12, "d": 1606, "e": 57310, "f": -1, "g": 2, "joinTimestamp": 1690384492, "knownNames": ["richardburnish", "forsenmods"], "logoutStreak": 0}, "4pILGNGFT5TmI0V2gaizRqy6PNE2": {"a": "diggydiggyFen", "b": "", "c": 12, "d": 1603, "e": 81170, "f": 17, "g": 2, "joinTimestamp": 1690384492, "knownNames": ["FenrirAdra", "Adramellech", "diggydiggyFen"], "logoutStreak": 0}, "4tgVhsAT19YixJvXeUPYV8YuH7H3": {"a": "Rickcatcher", "b": "", "c": 29, "d": 1396, "e": 29490, "f": -1, "g": 2, "joinTimestamp": 1726434226, "knownNames": ["Rickcatcher"], "logoutStreak": 0}, "5R3FMIbotYYHf8WtisAR0kcFOvV2": {"a": "alleonn2", "b": "", "c": 12, "d": 1468, "e": 22190, "f": 0, "g": 2, "joinTimestamp": 1727643865, "knownNames": ["Sixium", "alleonnb", "alleonn2"], "logoutStreak": 0}, "5aM3GPg0ahZocKzFudrSkKwxzHv2": {"a": "Sssource5", "b": "", "c": 40, "d": 1428, "e": 79220, "f": 14, "g": 2, "joinTimestamp": 1690384492, "knownNames": ["Sssource5"], "logoutStreak": 0}, "5s1ENyx9LoQafVRqv8xU7DGYSMB2": {"a": "Bakamage1", "b": "", "c": 40, "d": 1424, "e": 33840, "f": 8, "g": 2, "joinTimestamp": 1690384492, "knownNames": ["Bakamage1"], "logoutStreak": 0}, "5yl1hqBHdFVcCLKDvGUOtko6BF82": {"a": "yatoMiner1", "b": "", "c": 40, "d": 1388, "e": 23200, "f": -1, "g": 2, "joinTimestamp": 1744578730, "knownNames": ["yatoMiner1"], "logoutStreak": 0}, "5ypTkHBt2gWc13k36hqu3TcsSQC3": {"a": "zie820", "b": "", "c": 12, "d": 1358, "e": 90230, "f": 17, "g": 2, "joinTimestamp": 1690384492, "knownNames": ["zie820"], "logoutStreak": 0}, "611ZkmXewFhGrvsE3jbFzF7hCqJ3": {"a": "TheGman", "b": "", "c": 4, "d": 1496, "e": 108309, "f": -1, "g": 0, "joinTimestamp": 1690384492, "knownNames": ["LavaFlame2 in disguise", "TheGman"], "logoutStreak": 0}, "62CgJani7xNbgedh8T94pnZH9b63": {"a": "RussianDood", "b": "", "c": 12, "d": 1494, "e": 1690, "f": 8, "g": 3, "joinTimestamp": 1773612096, "knownNames": ["RussianDood"], "logoutStreak": 0}, "6YQn3aMNVSQiB2TdxsNqQBl9qtG2": {"a": "InfosecSNAFE", "b": "", "c": 14, "d": 1066, "e": 44890, "f": 13, "g": 2, "joinTimestamp": 1691961823, "knownNames": ["InfosecSNAFE"], "logoutStreak": 6}, "6noH1om9nXWqzECU4mVsNVkQwJU2": {"a": "Dolious", "b": "", "c": 12, "d": 1054, "e": 42860, "f": 0, "g": 2, "joinTimestamp": 1690384492, "knownNames": ["Dolious"], "logoutStreak": 0}, "6tfCvkx6EqWZSoHRrUIBy99fum72": {"a": "Pickleyama", "b": "", "c": 22, "d": 1307, "e": 38720, "f": 9, "g": 2, "joinTimestamp": 1709505501, "knownNames": ["Pickleyama"], "logoutStreak": 0}, "6yLBjPArNYdsayanGUswl6iCs6C2": {"a": "standupmoss", "b": "", "c": 34, "d": 1156, "e": 45560, "f": 17, "g": 2, "joinTimestamp": 1707084753, "knownNames": ["standupmoss"], "logoutStreak": 0}, "771bb03gtFeFxg58SOBbyNKeyCH3": {"a": "ty_red", "b": "", "c": 12, "d": 1518, "e": 27220, "f": 2, "g": 2, "joinTimestamp": 1749417620, "knownNames": ["sandokan620", "killermenb", "ty_red"], "logoutStreak": 0}, "7V3l05EEXYQlwNl54IU6pRQFsaJ2": {"a": "Oxydd3", "b": "", "c": 40, "d": 1279, "e": 34680, "f": 10, "g": 2, "joinTimestamp": 1702851666, "knownNames": ["oxydd", "Oxydd3"], "logoutStreak": 0}, "7a3qDllp1TN06UmGlEXEg90AyCe2": {"a": "Sbrodolo", "b": "", "c": 12, "d": 1270, "e": 1070, "f": -1, "g": 3, "joinTimestamp": 1774821639, "knownNames": ["Sbrodolo"], "logoutStreak": 0}, "7fdVBKmjuUOOIrElz6OxZykhxJH3": {"a": "KnightRevent", "b": "", "c": 12, "d": 1260, "e": 25420, "f": 10, "g": 2, "joinTimestamp": 1737324013, "knownNames": ["LightRevent", "JourneyRevent", "KnightRevent"], "logoutStreak": 0}, "7wn0no3JYXZNRyiHxUe78dSdGWG3": {"a": "Yung_Meme", "b": "", "c": 14, "d": 1376, "e": 52900, "f": 8, "g": 2, "joinTimestamp": 1690384492, "knownNames": ["Yung_Meme"], "logoutStreak": 0}, "87pGEs2ISaTSnGnoww2nkuiG9Nw2": {"a": "GertrazGWPE4", "b": "", "c": 12, "d": 1476, "e": 28940, "f": 17, "g": 2, "joinTimestamp": 1731276776, "knownNames": ["GertrazGWPE7", "GertrazGWPE4"], "logoutStreak": 0}, "8X2ZWXpvRhU45INmuTp3ZAcuAoO2": {"a": "MrClunkers", "b": "", "c": 40, "d": 1404, "e": 52090, "f": 8, "g": 2, "joinTimestamp": 1691961823, "knownNames": ["MrClunkers"], "logoutStreak": 0}, "8tCNQQOKgDeckxtxcE8jt5mcY6x1": {"a": "DemonCleaner", "b": "", "c": 14, "d": 1290, "e": 29000, "f": 17, "g": 2, "joinTimestamp": 1740952938, "knownNames": ["DemonCleaner"], "logoutStreak": 0}, "9iPLVd2pQpMw5lV5wUSEv7uPsPm2": {"a": "VanGodric", "b": "", "c": 40, "d": 1205, "e": 17560, "f": 10, "g": 2, "joinTimestamp": 1742767678, "knownNames": ["VanGodric"], "logoutStreak": 5}, "9wKC70GdavMbkrpqQj2X3ywS5gq2": {"a": "strongbad12", "b": "", "c": 12, "d": 427, "e": 1780, "f": 17, "g": 3, "joinTimestamp": 1774217500, "knownNames": ["strongbad12"], "logoutStreak": 0}, "AQ5gqyOjYJNdGM7awm2RuNtO5t22": {"a": "BadchimbayMel", "b": "", "c": 12, "d": 1265, "e": 28380, "f": 17, "g": 2, "joinTimestamp": 1726434226, "knownNames": ["BadchimbayMelt", "BadchimbayMel"], "logoutStreak": 1}, "AZx50yw5XqUeESrEy6B38YVv8L92": {"a": "one_again", "b": "", "c": 12, "d": 1293, "e": 1040, "f": 4, "g": 4, "joinTimestamp": 1774217500, "knownNames": ["one_again"], "logoutStreak": 0}, "AoF1VtcFh3TfpGS6ch0u48IaCxN2": {"a": "Momma_Crim", "b": "", "c": 4, "d": 1141, "e": 6600, "f": 17, "g": 2, "joinTimestamp": 1763330655, "knownNames": ["Momma_Crim"], "logoutStreak": 0}, "Az194XpVfUgiorJB3tHuwlbGCU73": {"a": "SqUiReSnOw", "b": "", "c": 12, "d": 1350, "e": 22030, "f": 17, "g": 2, "joinTimestamp": 1726434226, "knownNames": ["SqUiReSnOw"], "logoutStreak": 0}, "BE1eGDCMGWaDcBtFh47CVcLWyOk2": {"a": "erbeisst", "b": "", "c": 40, "d": 1250, "e": 51960, "f": 17, "g": 2, "joinTimestamp": 1690384492, "knownNames": ["erbeisst"], "logoutStreak": 0}, "BNaWeJ4GSYZYOCI6oeQckoLy55J2": {"a": "Bubblersz", "b": "", "c": 29, "d": 1323, "e": 122190, "f": 17, "g": 2, "joinTimestamp": 1690384492, "knownNames": ["IflylikeEGAL", "Bubblersz"], "logoutStreak": 0}, "BQ0VCx4kRuW2uHcBpKBsO20J2I03": {"a": "Deadxarrival2", "b": "", "c": 29, "d": 685, "e": 40670, "f": 8, "g": 2, "joinTimestamp": 1690384492, "knownNames": ["Deadxarrival2"], "logoutStreak": 0}, "Bm1JGKCmirSilO17QMwCwsFwbWw1": {"a": "Darkgolf1205", "b": "", "c": 14, "d": 1340, "e": 71420, "f": 7, "g": 2, "joinTimestamp": 1690384492, "knownNames": ["DarkGolf", "Rawker", "SimplyAsh", "Darkgolf1205"], "logoutStreak": 0}, "Bn8IzDwvflcl9cZp8KFXI0fdQr02": {"a": "arcadeash", "b": "", "c": 12, "d": 1336, "e": 37100, "f": 17, "g": 2, "joinTimestamp": 1712524012, "knownNames": ["arcadeash"], "logoutStreak": 0}, "BoYqOtgNKJXdvgE0H9KfxR0hXpj1": {"a": "Arew68", "b": "", "c": 40, "d": 1280, "e": 41120, "f": 17, "g": 2, "joinTimestamp": 1706479315, "knownNames": ["Arew68", "Arew65", "Arew69"], "logoutStreak": 0}, "BrMNRZmKmYZ7l6MhcfZeSgExubm1": {"a": "bruisermeta", "b": "", "c": 4, "d": 1243, "e": 70220, "f": 17, "g": 2, "joinTimestamp": 1690384492, "knownNames": ["bruisermeta"], "logoutStreak": 0}, "BuCWdFzourcA56BrYMdOLcaPqPz2": {"a": "robokn1ght", "b": "", "c": 14, "d": 1238, "e": 67580, "f": 14, "g": 2, "joinTimestamp": 1690384492, "knownNames": ["robokn1ght"], "logoutStreak": 0}, "BwDzmF0QXAd4rpnto99fBdbWA5X2": {"a": "Kachowt", "b": "", "c": 14, "d": 907, "e": 26700, "f": 17, "g": 2, "joinTimestamp": 1717969353, "knownNames": ["Kachowt"], "logoutStreak": 0}, "BymcpvBMp7PWJgZsSHWJK8QGAFF2": {"a": "WeaselStampede", "b": "", "c": 14, "d": 1297, "e": 161428, "f": 14, "g": 1, "joinTimestamp": 1690384492, "knownNames": ["WeaselStampede"], "logoutStreak": 0}, "C6DLeDO722gRv3FMRebQMMqgeX52": {"a": "WeGoOnceAgain", "b": "", "c": 12, "d": 1548, "e": 51880, "f": -1, "g": 2, "joinTimestamp": 1706479315, "knownNames": ["WeGoOnceAgain"], "logoutStreak": 0}, "CYRFrrHxeoTG4WNWHImLEqjhkNi2": {"a": "MuiMain", "b": "", "c": 12, "d": 1501, "e": 38650, "f": 17, "g": 2, "joinTimestamp": 1726434226, "knownNames": ["MuiMain"], "logoutStreak": 0}, "Cwbsg7rl9XW7rlQWt2UK6Td11Wq2": {"a": "BenSchw", "b": "", "c": 34, "d": 1475, "e": 23660, "f": 17, "g": 2, "joinTimestamp": 1743973863, "knownNames": ["BenSchw"], "logoutStreak": 0}, "Eb4whts1MrOXuQu8VSlElryPhj22": {"a": "Gray_Foxxx2", "b": "", "c": 40, "d": 1179, "e": 61160, "f": 5, "g": 2, "joinTimestamp": 1690384492, "knownNames": ["Gray_Foxxx", "Gray_Foxxx2"], "logoutStreak": 2}, "Eiev2FyNxRPuEA1N899F69m6sy92": {"a": "pitochui", "b": "", "c": 40, "d": 1326, "e": 15470, "f": 0, "g": 2, "joinTimestamp": 1745182550, "knownNames": ["pitochui"], "logoutStreak": 0}, "FBtT8R2JPadp9JOjPa7oKmL6WuB3": {"a": "Noyderan", "b": "", "c": 22, "d": 1314, "e": 64750, "f": 17, "g": 2, "joinTimestamp": 1690384492, "knownNames": ["Plicker", "Noyderan"], "logoutStreak": 0}, "FcajwZOXkyZeQRJK0mqvkoOGjtJ3": {"a": "X_c_a_l", "b": "", "c": 40, "d": 1326, "e": 123320, "f": 8, "g": 2, "joinTimestamp": 1690384492, "knownNames": ["X_c_a_l"], "logoutStreak": 0}, "FdemX0K8dzO70Iy8Df2vgywzIPI3": {"a": "PachaTree", "b": "", "c": 40, "d": 1450, "e": 63220, "f": 0, "g": 2, "joinTimestamp": 1690384492, "knownNames": ["PachaTree"], "logoutStreak": 0}, "Fe0twJB8hXamJf5iYE9vzXsOiVr2": {"a": "Carpentah", "b": "", "c": 40, "d": 623, "e": 14170, "f": 0, "g": 2, "joinTimestamp": 1726434226, "knownNames": ["Carpentah"], "logoutStreak": 0}, "FjhsGlsVY6gJdpnbMv1OdamjP7A2": {"a": "TEI0H", "b": "", "c": 34, "d": 1501, "e": 77560, "f": 17, "g": 2, "joinTimestamp": 1703457823, "knownNames": ["TEI0H"], "logoutStreak": 0}, "HEPc5TpmFQZWOyusBVfZabKjaa52": {"a": "Bradael", "b": "", "c": 14, "d": 1324, "e": 13890, "f": -1, "g": 2, "joinTimestamp": 1750021203, "knownNames": ["Bradael"], "logoutStreak": 0}, "I72MDldCB4RRrg3geKO7vgmqaz32": {"a": "allolllearch", "b": "", "c": 29, "d": 1424, "e": 17220, "f": 17, "g": 2, "joinTimestamp": 1745787707, "knownNames": ["allolllearch"], "logoutStreak": 0}, "IAiCUCyoWTbEqokcWalQIV3gLXY2": {"a": "Malikur", "b": "", "c": 34, "d": 1395, "e": 14270, "f": 17, "g": 2, "joinTimestamp": 1745182550, "knownNames": ["Malikur"], "logoutStreak": 0}, "IHhPl4pxJGR4mTp68kRvEHqUkjW2": {"a": "FNATMaverick", "b": "", "c": 40, "d": 1212, "e": 15140, "f": 10, "g": 2, "joinTimestamp": 1749417620, "knownNames": ["FNATMaverick"], "logoutStreak": 0}, "JHUGhnKrtDN0GSVSmqDFyE2qmaU2": {"a": "Redban", "b": "", "c": 12, "d": 850, "e": 115007, "f": 8, "g": 2, "joinTimestamp": 1690384492, "knownNames": ["Redban"], "logoutStreak": 0}, "JfDu1RV8ihVyjrib217WN1NYZOh2": {"a": "chucy", "b": "", "c": 14, "d": 1214, "e": 58510, "f": 6, "g": 2, "joinTimestamp": 1690384492, "knownNames": ["chucy"], "logoutStreak": 0}, "JpF01oEhzYYcOsi4Xht2GXsHp2l1": {"a": "Security2022", "b": "", "c": 14, "d": 643, "e": 21680, "f": 17, "g": 2, "joinTimestamp": 1730671402, "knownNames": ["Security2022"], "logoutStreak": 0}, "JqrN0dlMoHYnMrKM4rYbTaTaL1q1": {"a": "Reemang", "b": "", "c": 34, "d": 1359, "e": 77960, "f": 0, "g": 2, "joinTimestamp": 1690384492, "knownNames": ["Reemang"], "logoutStreak": 0}, "KqyFvIR6pmSVdv6dm0hRSkYAKLo1": {"a": "BumcheRD", "b": "", "c": 12, "d": 1289, "e": 27270, "f": 0, "g": 2, "joinTimestamp": 1730671402, "knownNames": ["BumcheRD"], "logoutStreak": 0}, "L7auE726kgg4OMU77JAmYReE5r02": {"a": "Windy_Bean", "b": "", "c": 29, "d": 1041, "e": 59630, "f": 17, "g": 2, "joinTimestamp": 1690384492, "knownNames": ["Windy_Bean"], "logoutStreak": 0}, "Lfpiajq4atWD4uAlwuKMTZaBUn03": {"a": "Idan21", "b": "", "c": 14, "d": 1012, "e": 2070, "f": -1, "g": 3, "joinTimestamp": 1769983458, "knownNames": ["Idan21"], "logoutStreak": 0}, "M6f2Og5erBNoV3brgd75STZoZm33": {"a": "war20hat", "b": "", "c": 14, "d": 1214, "e": 68070, "f": 17, "g": 2, "joinTimestamp": 1690384492, "knownNames": ["war20hat"], "logoutStreak": 1}, "Mpjdp2SKWqS0GANVPUnPann5V9f2": {"a": "Chevy_Chase", "b": "", "c": 4, "d": 1071, "e": 64680, "f": 17, "g": 2, "joinTimestamp": 1690384492, "knownNames": ["Alison_Brie", "Chevy_Chase"], "logoutStreak": 0}, "Neb9MjUwxuMbDqHBKWWhFAeMKlB2": {"a": "Vendryth", "b": "", "c": 40, "d": 1072, "e": 58520, "f": 8, "g": 2, "joinTimestamp": 1690384492, "knownNames": ["Vendryth"], "logoutStreak": 0}, "PPg39E2PYjRTRQKZMPloe6Ms8RS2": {"a": "Merladonna", "b": "", "c": 40, "d": 1462, "e": 29340, "f": 17, "g": 2, "joinTimestamp": 1731276776, "knownNames": ["Metchivel", "Merladonna"], "logoutStreak": 0}, "PVaA4XRS8VfMyZozabnKtKcItME2": {"a": "anvilkolesi", "b": "", "c": 22, "d": 1002, "e": 11640, "f": 17, "g": 2, "joinTimestamp": 1736719677, "knownNames": ["anvilkolesi"], "logoutStreak": 0}, "PjPE6X4vfNMnHfhrJI30gotbESg1": {"a": "oaklayy", "b": "", "c": 40, "d": 1253, "e": 25840, "f": 17, "g": 2, "joinTimestamp": 1709505501, "knownNames": ["oaklayy"], "logoutStreak": 0}, "QQBdcqx5sBMiOuqevfFAzYGoys32": {"a": "TheAphelion", "b": "", "c": 4, "d": 904, "e": 62350, "f": 17, "g": 2, "joinTimestamp": 1690384492, "knownNames": ["TheAphelion"], "logoutStreak": 0}, "QQjhIsHSHLZGW5hagKQLyHr99uA3": {"a": "Sarth7", "b": "", "c": 40, "d": 1502, "e": 34370, "f": 17, "g": 2, "joinTimestamp": 1691961823, "knownNames": ["Sarth7"], "logoutStreak": 0}, "Qg2g1z4AT2NHHvNe65gv3khI1rf1": {"a": "Angel_X", "b": "", "c": 12, "d": 1364, "e": 105930, "f": 17, "g": 2, "joinTimestamp": 1690384492, "knownNames": ["Merlinz_X", "Angel_X"], "logoutStreak": 0}, "R6QeC52aMmPM30Tq9V97SMRrPGO2": {"a": "lamoiroth_7", "b": "", "c": 29, "d": 1073, "e": 65290, "f": 14, "g": 2, "joinTimestamp": 1690384492, "knownNames": ["lamoiroth_7"], "logoutStreak": 3}, "RHYoqluSn4bpAtv6Fl4dxSlYiaM2": {"a": "mogman", "b": "", "c": 12, "d": 732, "e": 1310, "f": -1, "g": 3, "joinTimestamp": 1773007427, "knownNames": ["mogman"], "logoutStreak": 0}, "RkJ3cqxtUbfdkl9UBeOShu3B0nF2": {"a": "Rurunai", "b": "", "c": 4, "d": 1436, "e": 4370, "f": 17, "g": 2, "joinTimestamp": 1769378406, "knownNames": ["Rurunai"], "logoutStreak": 0}, "SC24kqaHKyTo0jf2ApMN2xz54Ef1": {"a": "Sphenw", "b": "", "c": 12, "d": 1198, "e": 40790, "f": 17, "g": 2, "joinTimestamp": 1690384492, "knownNames": ["Sphenw"], "logoutStreak": 0}, "SHQsa7iPGzYnsxqnKnELWr8uXii1": {"a": "Cavaloman", "b": "", "c": 12, "d": 1528, "e": 76300, "f": 10, "g": 2, "joinTimestamp": 1702851666, "knownNames": ["TioSuiken", "Sr_Madruguinha", "Ligeirinha", "Mago_Pato", "Jhosefina", "Cavaloman"], "logoutStreak": 0}, "SXkuAmOl4sbgsVOC89bPbGsiBqX2": {"a": "popeye36", "b": "", "c": 12, "d": 1433, "e": 24970, "f": 17, "g": 2, "joinTimestamp": 1739743208, "knownNames": ["popeye34", "popeye36", "popeye32"], "logoutStreak": 0}, "ScS88eYG1XOHhBUoaHfRssX2Nc52": {"a": "Tarnsy", "b": "", "c": 40, "d": 1021, "e": 39070, "f": 0, "g": 2, "joinTimestamp": 1717969353, "knownNames": ["Tarnsy"], "logoutStreak": 0}, "SdcO0wOJJjQt3njaBMK80m2LbMy1": {"a": "slopyjoe1", "b": "", "c": 34, "d": 1189, "e": 7760, "f": -1, "g": 2, "joinTimestamp": 1763330655, "knownNames": ["slopyjoe1"], "logoutStreak": 0}, "TADAgKURVkVeG5Ejcpj2XWSe0U12": {"a": "Bananen999", "b": "", "c": 40, "d": 1302, "e": 3820, "f": -1, "g": 2, "joinTimestamp": 1769983458, "knownNames": ["Bananen999"], "logoutStreak": 0}, "TAtr12IwodTgT73Hg17ApK8xLtz2": {"a": "Irishrosie", "b": "", "c": 14, "d": 647, "e": 42300, "f": 0, "g": 2, "joinTimestamp": 1690384492, "knownNames": ["Irishrosie"], "logoutStreak": 0}, "TLRohJRKxWdzb5k5znEuxWFcQYG3": {"a": "ricker", "b": "", "c": 40, "d": 1129, "e": 34970, "f": 17, "g": 2, "joinTimestamp": 1714942962, "knownNames": ["ricker"], "logoutStreak": 0}, "TPExrGecbSUW89jaNdI6ySxTTaT2": {"a": "Etkid09", "b": "", "c": 14, "d": 1206, "e": 49700, "f": 13, "g": 2, "joinTimestamp": 1690384492, "knownNames": ["Etkid09"], "logoutStreak": 0}, "TxZOBkkPxQUQR53lPsS5TDC6Et23": {"a": "szlaly", "b": "", "c": 40, "d": 1237, "e": 42590, "f": 17, "g": 2, "joinTimestamp": 1690384492, "knownNames": ["szlaly"], "logoutStreak": 0}, "UJfkJF95NAZXU5zeFCcN6vvfsnf1": {"a": "bennyislost4", "b": "", "c": 4, "d": 1308, "e": 93180, "f": 8, "g": 2, "joinTimestamp": 1690384492, "knownNames": ["bennyislost4"], "logoutStreak": 0}, "Uzs2syUu8dMPTbIoXjhlBDrIAqI3": {"a": "ProdigyHero", "b": "", "c": 12, "d": 1487, "e": 20340, "f": 0, "g": 2, "joinTimestamp": 1745182550, "knownNames": ["ProdigyShaman", "ProdigyHunter", "ProdigyHero"], "logoutStreak": 0}, "Vpb1ZaJYHHMaVU85udLYsAdnG7n1": {"a": "Magicyak", "b": "", "c": 40, "d": 1302, "e": 32620, "f": 17, "g": 2, "joinTimestamp": 1702851666, "knownNames": ["Mineyak", "Boatyak", "Magicyak"], "logoutStreak": 0}, "WAr5pDJ9ePevI7I7Toy4dcBv7Ik2": {"a": "Addy0", "b": "", "c": 14, "d": 1123, "e": 54600, "f": 17, "g": 2, "joinTimestamp": 1712524012, "knownNames": ["Addy0"], "logoutStreak": 10}, "WPzY3ZPAssPxI5b2TJaMXTIhbNF3": {"a": "GrumpiWiz", "b": "", "c": 40, "d": 1520, "e": 53640, "f": 17, "g": 2, "joinTimestamp": 1690384492, "knownNames": ["GrumpiWiz", "GrumpMinorMiner", "99999Gronk"], "logoutStreak": 0}, "WYGcO8duMlejS0M1wtegumWJ24o1": {"a": "Vorkez", "b": "", "c": 12, "d": 1594, "e": 9360, "f": -1, "g": 2, "joinTimestamp": 1764540021, "knownNames": ["Vorkez"], "logoutStreak": 0}, "X7eE93BJxZaGzhWXu5XICEcCzv63": {"a": "rjslayer", "b": "", "c": 34, "d": 1015, "e": 40190, "f": 14, "g": 2, "joinTimestamp": 1707689056, "knownNames": ["rjslayer"], "logoutStreak": 0}, "XAt0jVyapSSiiYdMYuVlP8tfIMz1": {"a": "projectbow", "b": "", "c": 29, "d": 1329, "e": 24040, "f": 9, "g": 2, "joinTimestamp": 1743369460, "knownNames": ["projectbow"], "logoutStreak": 0}, "XERjgMqShPTX4uuJUlEeJssUABE2": {"a": "daydream_king", "b": "", "c": 1, "d": 1244, "e": 81720, "f": 17, "g": 2, "joinTimestamp": 1690384492, "knownNames": ["sirBraska", "siravalanch", "daydream_king"], "logoutStreak": 0}, "XllC073EOLNCO0aA3uCGYmnSoox1": {"a": "Draevyhn", "b": "", "c": 40, "d": 1532, "e": 41510, "f": 17, "g": 2, "joinTimestamp": 1730671402, "knownNames": ["Dreywiz", "Drayven", "Dreyarch", "Draevyhn"], "logoutStreak": 0}, "Y07oXpOpfiV56eHVgMcNcla9FwH2": {"a": "Pawneth", "b": "", "c": 29, "d": 742, "e": 660, "f": -1, "g": 4, "joinTimestamp": 1772403613, "knownNames": ["Pawneth"], "logoutStreak": 5}, "YHCA0Dcgp2OQVv0hVdqrH27uaA12": {"a": "Hikari_Yami", "b": "", "c": 12, "d": 1606, "e": 22470, "f": 17, "g": 2, "joinTimestamp": 1736719677, "knownNames": ["Hikari_Yami"], "logoutStreak": 0}, "YUdhsRzdKgQzEemycNpdaRoEAEb2": {"a": "Aaqua", "b": "", "c": 14, "d": 1261, "e": 78720, "f": 17, "g": 2, "joinTimestamp": 1690384492, "knownNames": ["Aaqua"], "logoutStreak": 0}, "YypdhI6awLTLwPhh2I49rKbPIy42": {"a": "ryanizme", "b": "", "c": 22, "d": 1119, "e": 73332, "f": 17, "g": 2, "joinTimestamp": 1690384492, "knownNames": ["ryanizme"], "logoutStreak": 0}, "ZSSaFvbREWbzPm3PeOv1cVJPtrw1": {"a": "N0Taiyo", "b": "", "c": 40, "d": 1536, "e": 32400, "f": -1, "g": 2, "joinTimestamp": 1725829415, "knownNames": ["GiffyBot", "NotTaiyo", "N0Taiyo"], "logoutStreak": 0}, "ZdGhTzbsX1URtvDXZbRCCDAlhu13": {"a": "Candlewight", "b": "", "c": 22, "d": 364, "e": 122250, "f": 17, "g": 2, "joinTimestamp": 1690384492, "knownNames": ["Candlewight"], "logoutStreak": 0}, "aH7hg4Qp4KQoJNLRi0kqbKoHn1X2": {"a": "kushal_jr", "b": "", "c": 40, "d": 435, "e": 960, "f": 17, "g": 4, "joinTimestamp": 1772403613, "knownNames": ["kushal_jr"], "logoutStreak": 1}, "aesXRPB1CyfNTu7kKTGSNWehPvv1": {"a": "BobBitBot", "b": "", "c": 40, "d": 1339, "e": 53730, "f": -1, "g": 2, "joinTimestamp": 1690384492, "knownNames": ["boombotbam", "BobBitBot"], "logoutStreak": 0}, "avSu8n8M2CXwAed9ehvnvFO4zhx1": {"a": "BloodFallen17", "b": "", "c": 22, "d": 896, "e": 47660, "f": 14, "g": 2, "joinTimestamp": 1690384492, "knownNames": ["BloodFallen17"], "logoutStreak": 0}, "ayR4xrwHSOVDf1tsGodE7xh3N9z2": {"a": "atarminer", "b": "", "c": 12, "d": 1079, "e": 63410, "f": 8, "g": 2, "joinTimestamp": 1690384492, "knownNames": ["magic_woosh", "atarminer"], "logoutStreak": 0}, "bCoHNiMXhBMcTYMbXZcv2mkofA93": {"a": "FightorFight", "b": "", "c": 34, "d": 1070, "e": 49600, "f": 17, "g": 2, "joinTimestamp": 1690384492, "knownNames": ["FightorFight"], "logoutStreak": 0}, "bKfyliE8sfaRPRRk6tmAlvBpb4t1": {"a": "SO10", "b": "", "c": 4, "d": 1190, "e": 27540, "f": 17, "g": 2, "joinTimestamp": 1726434226, "knownNames": ["Chronu2", "finite", "SO10"], "logoutStreak": 0}, "bRcdMIkYOFVRUJaoBrsURfgkHMW2": {"a": "divide_bye_zero", "b": "", "c": 22, "d": 1142, "e": 75450, "f": 9, "g": 2, "joinTimestamp": 1690384492, "knownNames": ["divide_bye_zero"], "logoutStreak": 0}, "bljRj0ak4tSd8fteQQFqtiGOMRq1": {"a": "ellip992", "b": "", "c": 14, "d": 692, "e": 8990, "f": 6, "g": 2, "joinTimestamp": 1730671402, "knownNames": ["ellip99", "ellip992"], "logoutStreak": 0}, "c7JPyA1g0dV22AjnSqe1CCAcumy2": {"a": "Raythein", "b": "", "c": 14, "d": 1366, "e": 19280, "f": 17, "g": 2, "joinTimestamp": 1736719677, "knownNames": ["Raythein"], "logoutStreak": 0}, "cGaPc95YHcXyhRNjuYj9lwlTE5P2": {"a": "auuxjman", "b": "", "c": 4, "d": 1160, "e": 50020, "f": -1, "g": 2, "joinTimestamp": 1690384492, "knownNames": ["auuxjman"], "logoutStreak": 0}, "cObMZanEZXNCE8O4b5k5n5HjOmh2": {"a": "Sunsh1ne", "b": "", "c": 14, "d": 1385, "e": 56570, "f": 14, "g": 2, "joinTimestamp": 1690384492, "knownNames": ["Sunsh1ne"], "logoutStreak": 0}, "ciArArsYPmTfCMgVs6zaNUKQBGq2": {"a": "Iron_Luck", "b": "", "c": 4, "d": 772, "e": 123960, "f": 8, "g": 2, "joinTimestamp": 1690384492, "knownNames": ["Iron_Luck"], "logoutStreak": 1}, "d27ZwTlb4QR0dKeVFMOU3mnnW6s1": {"a": "5OhBark", "b": "", "c": 12, "d": 1636, "e": 130460, "f": 14, "g": 2, "joinTimestamp": 1690384492, "knownNames": ["5OhTree", "5OhTwig", "5OhBark"], "logoutStreak": 0}, "dBok68yB5FM09EV9itN9sgBJ8r33": {"a": "journeyleelee", "b": "", "c": 4, "d": 1370, "e": 37520, "f": 17, "g": 2, "joinTimestamp": 1730671402, "knownNames": ["Blip_DoopPoolp", "journeyleelee"], "logoutStreak": 0}, "dpYnNYTl3LO7bJ9JGILUruWhTAt1": {"a": "afflickted", "b": "", "c": 40, "d": 1512, "e": 74030, "f": 17, "g": 2, "joinTimestamp": 1690384492, "knownNames": ["afflickted"], "logoutStreak": 0}, "eld77FfnIRUOOZuag3fk3Np3DyC3": {"a": "muffinatrix", "b": "", "c": 34, "d": 1202, "e": 7160, "f": 17, "g": 2, "joinTimestamp": 1763330655, "knownNames": ["muffinatrix"], "logoutStreak": 0}, "ezHAsRMILUh6v53CDpUYNPCRh5E2": {"a": "Viiser", "b": "", "c": 14, "d": 1029, "e": 27010, "f": 0, "g": 2, "joinTimestamp": 1730671402, "knownNames": ["Viiser"], "logoutStreak": 0}, "gsfl9yNGqYWhG6dV7428exLXezt1": {"a": "dannienotr", "b": "", "c": 12, "d": 1136, "e": 48870, "f": 17, "g": 2, "joinTimestamp": 1690384492, "knownNames": ["luckyJerald", "dannienotr", "jackisreal"], "logoutStreak": 0}, "h17gHcE90xcHHpNuJSKYhlE4ukZ2": {"a": "H5YD0S", "b": "", "c": 4, "d": 1157, "e": 62170, "f": 17, "g": 2, "joinTimestamp": 1690384492, "knownNames": ["H5YD0S"], "logoutStreak": 0}, "hDSQVIKEMQUyif5uypj4g02YyUd2": {"a": "KINGLOKO85", "b": "", "c": 12, "d": 1168, "e": 110540, "f": 8, "g": 2, "joinTimestamp": 1690384492, "knownNames": ["KINGLOKO85"], "logoutStreak": 0}, "hhXkT0ZC6dX1TOTxelYhA8vhwDX2": {"a": "Vereic", "b": "", "c": 40, "d": 1199, "e": 6320, "f": 17, "g": 2, "joinTimestamp": 1763330655, "knownNames": ["Vereic"], "logoutStreak": 0}, "hm7zr1u5X4hDSEeHrxgrUFa7XtW2": {"a": "salemn", "b": "", "c": 34, "d": 1352, "e": 48240, "f": 14, "g": 2, "joinTimestamp": 1690384492, "knownNames": ["salemn"], "logoutStreak": 0}, "hxturNt10KdKyQ14oWdNLCjkvmn1": {"a": "Averip", "b": "", "c": 12, "d": 1433, "e": 82260, "f": 8, "g": 2, "joinTimestamp": 1690384492, "knownNames": ["Averip"], "logoutStreak": 0}, "iZ7PS913iaW0ae93TvvP7w4qfy33": {"a": "NateMaMan", "b": "", "c": 34, "d": 858, "e": 30240, "f": 17, "g": 2, "joinTimestamp": 1726434226, "knownNames": ["NateMaMan"], "logoutStreak": 0}, "ifLQnAk7BbVnxC5UO3IvVaPT6c73": {"a": "DukeXV", "b": "", "c": 40, "d": 1335, "e": 16630, "f": 10, "g": 2, "joinTimestamp": 1737324013, "knownNames": ["DukeXV"], "logoutStreak": 0}, "iph5I75sRhQow8YQmLVqbt44QeH3": {"a": "Tibreon", "b": "", "c": 12, "d": 1586, "e": 80420, "f": 17, "g": 2, "joinTimestamp": 1690384492, "knownNames": ["Tibreon", "Ezril"], "logoutStreak": 0}, "j7XdhigDKFhXTaxc11m57KETPGJ2": {"a": "Applausey", "b": "", "c": 34, "d": 1501, "e": 111260, "f": 8, "g": 2, "joinTimestamp": 1690384492, "knownNames": ["Applausey"], "logoutStreak": 0}, "jATeD597qPOwyX79j2ontlxEuwH2": {"a": "SpeshlChops", "b": "", "c": 40, "d": 1360, "e": 69610, "f": -1, "g": 2, "joinTimestamp": 1690384492, "knownNames": ["SpeshlChops"], "logoutStreak": 0}, "jXSn6km5whcrTND49xDMhKFZiAz1": {"a": "ObamaDoNotCare", "b": "", "c": 40, "d": 1146, "e": 67020, "f": 8, "g": 2, "joinTimestamp": 1690384492, "knownNames": ["ObamaDontCare", "ObamaDoNotCare"], "logoutStreak": 0}, "jfkSqdz9TPP0j9BjGc0u0ocrlCF2": {"a": "RavensEcccccccc", "b": "", "c": 12, "d": 1400, "e": 24780, "f": 17, "g": 2, "joinTimestamp": 1737928866, "knownNames": ["LilRaven2306", "RavensEcccccccc"], "logoutStreak": 0}, "jmC9t7x3p1dIE6KayPRL6lb92zU2": {"a": "SussusAmongus5", "b": "", "c": 34, "d": 1350, "e": 70080, "f": 17, "g": 2, "joinTimestamp": 1690384492, "knownNames": ["SussusAmongus5"], "logoutStreak": 0}, "jvIKgyHc98NhQmrqo2D45HFKP853": {"a": "vdemort", "b": "", "c": 14, "d": 1134, "e": 138080, "f": 8, "g": 2, "joinTimestamp": 1690384492, "knownNames": ["vdemort"], "logoutStreak": 0}, "jyjNj8YUKkbPVE0VEqvb96NjkRs1": {"a": "Lady_Mileena", "b": "", "c": 40, "d": 1098, "e": 104290, "f": 17, "g": 2, "joinTimestamp": 1690384492, "knownNames": ["Lady_Mileena"], "logoutStreak": 0}, "kXK2ZxYiJMQkeWWdZ0eiPa1pwuz1": {"a": "LCA1", "b": "", "c": 12, "d": 1463, "e": 139276, "f": 8, "g": 2, "joinTimestamp": 1690384492, "knownNames": ["LCA6", "LCA1"], "logoutStreak": 0}, "kboX1MTcPJWvGQkHCLZ7QP3aUyq1": {"a": "Adieria", "b": "", "c": 12, "d": 1400, "e": 47480, "f": -1, "g": 2, "joinTimestamp": 1705269998, "knownNames": ["Adieria"], "logoutStreak": 0}, "kdqoN1vgg8bN0MQXeaCesADdAx03": {"a": "iDizzY", "b": "", "c": 22, "d": 1320, "e": 9470, "f": -1, "g": 2, "joinTimestamp": 1763330655, "knownNames": ["iiiiDizzY", "iDizzY"], "logoutStreak": 0}, "lLIdkYHnc9PxDH9r13PQKWapgTu1": {"a": "Awawaee", "b": "", "c": 22, "d": 1282, "e": 23150, "f": 0, "g": 2, "joinTimestamp": 1733090732, "knownNames": ["Awawaee"], "logoutStreak": 0}, "lcWBqQC1IrNDhzsfsV46dUJ4JHk2": {"a": "beater_of_meat", "b": "", "c": 12, "d": 1410, "e": 21290, "f": 17, "g": 2, "joinTimestamp": 1742767678, "knownNames": ["beater_of_meat"], "logoutStreak": 0}, "lvmuXNzjkBbJw8ODCQgLNzhuGKs1": {"a": "VessMaestro", "b": "", "c": 4, "d": 1402, "e": 107870, "f": 17, "g": 2, "joinTimestamp": 1690384492, "knownNames": ["VessMaestro"], "logoutStreak": 0}, "m0TQml7hmzbHnonH6vqE3DrzdjI3": {"a": "SorrowsFear", "b": "", "c": 12, "d": 1097, "e": 24690, "f": -1, "g": 2, "joinTimestamp": 1730671402, "knownNames": ["SorrowsFear"], "logoutStreak": 0}, "mPCluN0YvCS6Xj6WM5UeW7E6tio1": {"a": "SuggmaBallz", "b": "", "c": 29, "d": 1256, "e": 2630, "f": 17, "g": 2, "joinTimestamp": 1769983458, "knownNames": ["SuggmaBallz"], "logoutStreak": 3}, "mrnU1ZZUkGPmHSQYzEhLEImpu0c2": {"a": "Tony_Stork", "b": "", "c": 34, "d": 1274, "e": 70220, "f": 17, "g": 2, "joinTimestamp": 1690384492, "knownNames": ["Tony_Stork"], "logoutStreak": 0}, "n1NLDr9eiGcsvDu2a8GtFa6oTQn2": {"a": "RezSorc", "b": "", "c": 40, "d": 1175, "e": 15100, "f": 10, "g": 2, "joinTimestamp": 1746392291, "knownNames": ["Rezlark", "RezSorc"], "logoutStreak": 0}, "nRqzXmT36xbVEN64T39El086hxO2": {"a": "Shin_Hati", "b": "", "c": 34, "d": 1384, "e": 39900, "f": -1, "g": 2, "joinTimestamp": 1712524012, "knownNames": ["Shin_Hati"], "logoutStreak": 0}, "nhcuWRI79RahWCdrO9kiGRZZM0x2": {"a": "EllIB", "b": "", "c": 29, "d": 1195, "e": 4530, "f": 17, "g": 2, "joinTimestamp": 1769983458, "knownNames": ["EllIB"], "logoutStreak": 0}, "ntlBzFmXHWWAPQMkJpVaOVzRikw2": {"a": "warryx", "b": "", "c": 14, "d": 1269, "e": 24470, "f": 5, "g": 2, "joinTimestamp": 1730671402, "knownNames": ["archerblaster", "warryx"], "logoutStreak": 0}, "oAQalFQRnzc4TgBYximwvv6DV903": {"a": "sumbeech", "b": "", "c": 12, "d": 831, "e": 68960, "f": 8, "g": 2, "joinTimestamp": 1690384492, "knownNames": ["Cromag", "sumbeech"], "logoutStreak": 0}, "ocghnGzRj6aNt0IwCmCU3eGLkYJ3": {"a": "deus_mago", "b": "", "c": 40, "d": 1309, "e": 69640, "f": 17, "g": 2, "joinTimestamp": 1690384492, "knownNames": ["deus_mago"], "logoutStreak": 0}, "ohx3Tpvm6mN805eZuxHu6bSwIeW2": {"a": "skracken", "b": "", "c": 14, "d": 984, "e": 56580, "f": 17, "g": 2, "joinTimestamp": 1690384492, "knownNames": ["skracken"], "logoutStreak": 0}, "pYru7xzlxMgwLBkiOTpWaHa3ZAo1": {"a": "Hades12345", "b": "", "c": 12, "d": 1010, "e": 26300, "f": 17, "g": 2, "joinTimestamp": 1720991370, "knownNames": ["Hades12345"], "logoutStreak": 0}, "pelhsai0QGUpnU1rCuRMbaMCMo93": {"a": "Jeebys18h", "b": "", "c": 34, "d": 1438, "e": 26190, "f": 17, "g": 2, "joinTimestamp": 1749417620, "knownNames": ["Jeebys18h"], "logoutStreak": 0}, "qIpIlsKE67b1xht9oEJL39XarBN2": {"a": "Vncle", "b": "", "c": 12, "d": 1418, "e": 42020, "f": 17, "g": 2, "joinTimestamp": 1706479315, "knownNames": ["Dvddy", "Mvmmy", "Vncle"], "logoutStreak": 0}, "sBMQyEPrsaMyaIfIHyX9Lx9TT673": {"a": "maven1", "b": "", "c": 12, "d": 1219, "e": 46070, "f": 14, "g": 2, "joinTimestamp": 1690384492, "knownNames": ["dumbledoree", "maven1"], "logoutStreak": 0}, "steam_76561197964890535": {"a": "Vehlena", "b": "", "c": 40, "d": 1035, "e": 4240, "f": 17, "g": 2, "joinTimestamp": 1769378406, "knownNames": ["Vehlena"], "logoutStreak": 1}, "steam_76561197994148793": {"a": "ToxixAgi", "b": "", "c": 22, "d": 906, "e": 1420, "f": 17, "g": 3, "joinTimestamp": 1771192907, "knownNames": ["ToxixAgi"], "logoutStreak": 5}, "steam_76561197997664024": {"a": "nopardon", "b": "", "c": 22, "d": 587, "e": 120, "f": -1, "g": 5, "joinTimestamp": 1772403613, "knownNames": ["nopardon"], "logoutStreak": 2}, "steam_76561198011142833": {"a": "Hyper_Royal", "b": "", "c": 14, "d": 569, "e": 11150, "f": -1, "g": 2, "joinTimestamp": 1763330655, "knownNames": ["Hyper_Royal"], "logoutStreak": 0}, "steam_76561198072811453": {"a": "Sunicarus", "b": "", "c": 12, "d": 1637, "e": 5420, "f": 17, "g": 2, "joinTimestamp": 1770588316, "knownNames": ["Sunicarus"], "logoutStreak": 0}, "steam_76561198077496556": {"a": "nalasuu", "b": "", "c": 40, "d": 1302, "e": 6790, "f": 8, "g": 2, "joinTimestamp": 1764540021, "knownNames": ["nalasuu"], "logoutStreak": 0}, "steam_76561198118225251": {"a": "Megamage11", "b": "", "c": 40, "d": 1419, "e": 3810, "f": -1, "g": 2, "joinTimestamp": 1769983458, "knownNames": ["Megamage11"], "logoutStreak": 0}, "steam_76561198133296919": {"a": "Vehyron", "b": "", "c": 14, "d": 1200, "e": 5660, "f": 8, "g": 2, "joinTimestamp": 1763330655, "knownNames": ["Vehyron"], "logoutStreak": 0}, "steam_76561198163523322": {"a": "SleekSkydog50", "b": "", "c": 34, "d": 1277, "e": 5450, "f": 17, "g": 2, "joinTimestamp": 1768168882, "knownNames": ["SleekSkydog50"], "logoutStreak": 0}, "steam_76561198188488405": {"a": "Keikikyuu1", "b": "", "c": 12, "d": 1204, "e": 3060, "f": -1, "g": 2, "joinTimestamp": 1769378406, "knownNames": ["Keikikyuu1"], "logoutStreak": 0}, "steam_76561198202916790": {"a": "KubiyyoCZ_WIS", "b": "", "c": 40, "d": 1130, "e": 5280, "f": 17, "g": 2, "joinTimestamp": 1770588316, "knownNames": ["KubiyyoCZ_WIS"], "logoutStreak": 0}, "steam_76561198373849295": {"a": "Flummo6", "b": "", "c": 40, "d": 725, "e": 1620, "f": 0, "g": 3, "joinTimestamp": 1774217500, "knownNames": ["Flummo6"], "logoutStreak": 0}, "steam_76561199122758320": {"a": "kopaczcz", "b": "", "c": 12, "d": 1141, "e": 3010, "f": -1, "g": 2, "joinTimestamp": 1769983458, "knownNames": ["kopaczcz"], "logoutStreak": 0}, "steam_76561199224992648": {"a": "samsam606", "b": "", "c": 12, "d": 1360, "e": 2990, "f": -1, "g": 2, "joinTimestamp": 1769983458, "knownNames": ["samsam606"], "logoutStreak": 0}, "tCDLRV2mepdjxPC0xeuqCjCMoo23": {"a": "oddMonstr", "b": "", "c": 22, "d": 1245, "e": 22870, "f": 17, "g": 2, "joinTimestamp": 1702851666, "knownNames": ["oddMonstr"], "logoutStreak": 0}, "tRLuLmwVjXg3U6KsWyPqXm9zsJj1": {"a": "AniLuckHen", "b": "", "c": 12, "d": 1169, "e": 59340, "f": 13, "g": 2, "joinTimestamp": 1690384492, "knownNames": ["AniLuHen", "AniLuckHen"], "logoutStreak": 0}, "tZIsxF7Duhd3s2M6de0BUCbbVUX2": {"a": "Xarikue", "b": "", "c": 40, "d": 1382, "e": 106560, "f": 17, "g": 2, "joinTimestamp": 1690384492, "knownNames": ["Xarikue"], "logoutStreak": 0}, "tleFR1pm7mh0GPQuhqBwvfApA3C2": {"a": "EpicSmartz4", "b": "", "c": 12, "d": 1482, "e": 65110, "f": 8, "g": 2, "joinTimestamp": 1690384492, "knownNames": ["EpicSmartz", "EpicSmartz3", "EpicSmartz4"], "logoutStreak": 0}, "u1oKS8MhtWYnEyR0yBLGNuMIa5F2": {"a": "Bandrix", "b": "", "c": 12, "d": 1238, "e": 48380, "f": 17, "g": 2, "joinTimestamp": 1690384492, "knownNames": ["Bandrix"], "logoutStreak": 0}, "uC8Olg0tdMQ9O6lU6alDOzw1TOB2": {"a": "Smileone", "b": "", "c": 12, "d": 1426, "e": 56380, "f": 17, "g": 2, "joinTimestamp": 1714942962, "knownNames": ["Smileone"], "logoutStreak": 0}, "uTXRoryKvmUFsiWnycHxc3o8kCY2": {"a": "Geshaj", "b": "", "c": 40, "d": 1303, "e": 31100, "f": 17, "g": 2, "joinTimestamp": 1726434226, "knownNames": ["Geshhh", "Geshad", "Geshaj"], "logoutStreak": 0}, "uq8bE5yxdLgbRZQsn2QZ5F73vrv1": {"a": "Mozeps", "b": "", "c": 40, "d": 881, "e": 30230, "f": -1, "g": 2, "joinTimestamp": 1692566075, "knownNames": ["Mozeps"], "logoutStreak": 0}, "vIzegGyZDmTCfk0muhWHUO0mjX02": {"a": "Victorialas", "b": "", "c": 22, "d": 1002, "e": 26410, "f": 17, "g": 2, "joinTimestamp": 1704060380, "knownNames": ["Victorialas"], "logoutStreak": 0}, "vQhA2Y9l35P7YG6B3MiYZXjaSAx2": {"a": "Xnyl", "b": "", "c": 12, "d": 1358, "e": 51200, "f": -1, "g": 2, "joinTimestamp": 1699222009, "knownNames": ["Xnyl"], "logoutStreak": 0}, "vffaj826yBXB580fsHMbzDw7rc83": {"a": "AN0NYMOUSE", "b": "", "c": 12, "d": 1519, "e": 4680, "f": 0, "g": 2, "joinTimestamp": 1769983458, "knownNames": ["Oskyris", "AN0NYMOUSE"], "logoutStreak": 0}, "vpMjIogKt1U01jkPE5p45uQVW873": {"a": "BigSchmeller", "b": "", "c": 12, "d": 1333, "e": 25640, "f": 0, "g": 2, "joinTimestamp": 1717969353, "knownNames": ["BigSchmeller"], "logoutStreak": 0}, "wHryf3mGyEh1Qa9qKPWriwbe5Bz2": {"a": "Justrule02", "b": "", "c": 40, "d": 1009, "e": 63730, "f": 17, "g": 2, "joinTimestamp": 1690384492, "knownNames": ["Justrule02"], "logoutStreak": 0}, "wRGwBGMyxgPBeXL1VGmLTP1LmNj2": {"a": "lonkonk", "b": "", "c": 34, "d": 1434, "e": 79260, "f": -1, "g": 2, "joinTimestamp": 1690384492, "knownNames": ["lonkonk"], "logoutStreak": 0}, "wfxKS16KPbVA80PZAuDO9Cr9TRG3": {"a": "maseoflootofloo", "b": "", "c": 12, "d": 1407, "e": 2640, "f": 17, "g": 2, "joinTimestamp": 1771798244, "knownNames": ["maseoflootofloo"], "logoutStreak": 0}, "xTuaVKL019ZvDdRuA8wH0FleVOt2": {"a": "LeftRightCombo", "b": "", "c": 4, "d": 1416, "e": 2880, "f": -1, "g": 2, "joinTimestamp": 1769983458, "knownNames": ["LeftRightCombo"], "logoutStreak": 0}, "xrd3Ccr2gtVxtNAWDoKsy7JOLE73": {"a": "riverdawe", "b": "", "c": 22, "d": 1362, "e": 4820, "f": 17, "g": 2, "joinTimestamp": 1763330655, "knownNames": ["riverdawe"], "logoutStreak": 0}, "yAibSZ8GTcVszsVWdthnhP9rCV23": {"a": "Love_Is_Luck", "b": "", "c": 4, "d": 805, "e": 16130, "f": 17, "g": 2, "joinTimestamp": 1736719677, "knownNames": ["Love_Is_Luck"], "logoutStreak": 0}, "yJOGGKutUwM1wjDzaCuDhTWUIQR2": {"a": "Yetilicious", "b": "", "c": 40, "d": 1206, "e": 32140, "f": 17, "g": 2, "joinTimestamp": 1708293709, "knownNames": ["Yetilicious"], "logoutStreak": 0}, "yWOxIOIb1cXS8M5vSBK5SHQtK1A3": {"a": "BuffZam", "b": "", "c": 12, "d": 564, "e": 116220, "f": -1, "g": 2, "joinTimestamp": 1690384492, "knownNames": ["BuffZam"], "logoutStreak": 0}, "yilYnNy8zZgTixs6POCYVIlqwex1": {"a": "Nikel", "b": "", "c": 22, "d": 1265, "e": 21200, "f": -1, "g": 2, "joinTimestamp": 1737324013, "knownNames": ["Nikel"], "logoutStreak": 0}, "yvwA2HcCmSSpQB20TBZaiZKlM3e2": {"a": "lulpat", "b": "", "c": 12, "d": 1147, "e": 48040, "f": 10, "g": 2, "joinTimestamp": 1690384492, "knownNames": ["patflex", "lulpat"], "logoutStreak": 0}, "z45fX7UKMOdGqyJSyoEHGBFC1mO2": {"a": "fakebalmung", "b": "", "c": 40, "d": 1300, "e": 49740, "f": 10, "g": 2, "joinTimestamp": 1701037253, "knownNames": ["fakebalmung"], "logoutStreak": 0}, "zXVZc8l0hVXlszo9KOD8BjCsY4H3": {"a": "DivK1", "b": "", "c": 12, "d": 657, "e": 38870, "f": 10, "g": 2, "joinTimestamp": 1706479315, "knownNames": ["DivK1"], "logoutStreak": 3}}, "t": 1776028694}